Workbook

Sheet P&L WACD
A1: Company: 124667 - WorldACD Market Data B.V.
A3: Balance sheet / Profit and loss statement
A6: Rev distribution per FY | Q6: =Q19/SUM($Q$19:$AB$19) -> 0.074776031 | R6: =R19/SUM($Q$19:$AB$19) -> 0.083490441 | S6: =S19/SUM($Q$19:$AB$19) -> 0.075336585 | T6: =T19/SUM($Q$19:$AB$19) -> 0.07805418 | U6: =U19/SUM($Q$19:$AB$19) -> 0.081204745 | V6: =V19/SUM($Q$19:$AB$19) -> 0.080437813 | W6: =W19/SUM($Q$19:$AB$19) -> 0.08489432 | X6: =X19/SUM($Q$19:$AB$19) -> 0.08538783 | ... AB6: =AB19/SUM($Q$19:$AB$19) -> 0.092105148 | AC6: =AC19/SUM($AC$19:$AN$19) -> 0.074676379 | AD6: =AD19/SUM($AC$19:$AN$19) -> 0.081064474 | AE6: =AE19/SUM($AC$19:$AN$19) -> 0.079698561 | AF6: =AF19/SUM($AC$19:$AN$19) -> 0.082174781 | AG6: =AG19/SUM($AC$19:$AN$19) -> 0.080414804 | AH6: =AH19/SUM($AC$19:$AN$19) -> 0.081936249 | AI6: =AI19/SUM($AC$19:$AN$19) -> 0.084780069 | AJ6: =AJ19/SUM($AC$19:$AN$19) -> 0.086797608 | ... AN6: =AN19/SUM($AC$19:$AN$19) -> 0.087963471 | AO6: =AO19/SUM($AO$19:$AZ$19) -> 0.075923013 | AP6: =AP19/SUM($AO$19:$AZ$19) -> 0.07748022 | AQ6: =AQ19/SUM($AO$19:$AZ$19) -> 0.078177321 | AR6: =AR19/SUM($AO$19:$AZ$19) -> 0.073821908 | AS6: =AS19/SUM($AO$19:$AZ$19) -> 0.080140305 | AT6: =AT19/SUM($AO$19:$AZ$19) -> 0.086795626 | AU6: =AU19/SUM($AO$19:$AZ$19) -> 0.093264005 | AV6: =AV19/SUM($AO$19:$AZ$19) -> 0.088356974 | ... AZ6: =AZ19/SUM($AO$19:$AZ$19) -> 0.092860354
A7: Particulars | B7: 2022 | C7: 2022 | D7: 2022 | E7: 2022 | F7: 2022 | G7: 2022 | H7: 2022 | I7: 2022 | J7: 2022 | K7: 2022 | L7: 2022 | M7: 2022 | N7: 2023 | O7: 2023 | P7: 2023 | Q7: 2023 | R7: 2023 | S7: 2023 | T7: 2023 | U7: 2023 | V7: 2023 | W7: 2023 | X7: 2023 | Y7: 2023 | Z7: 2024 | AA7: 2024 | AB7: 2024 | AC7: 2024 | AD7: 2024 | AE7: 2024 | AF7: 2024 | AG7: 2024 | AH7: 2024 | AI7: 2024 | AJ7: 2024 | AK7: 2024 | AL7: 2025 | AM7: 2025 | AN7: 2025 | AO7: 2025 | AP7: 2025 | AQ7: 2025 | AR7: 2025 | AS7: 2025 | AT7: 2025 | AU7: 2025 | AV7: 2025 | AW7: 2025 | AX7: 2026 | AY7: 2026 | AZ7: 2026 | BA7: 2026 | BB7: 2026 | BC7: 2026 | BD7: 2026 | BE7: 2026 | BF7: 2026 | BG7: 2025 | BH7: 2024 | BI7: 2023 | BJ7: FY2027 | BK7: FY2026 | BL7: FY2025 | BM7: FY2024 | BN7: FY2023 | BO7: FY2022 | BP7: Remarks
B8: January | C8: Februari | D8: March | E8: April | F8: May | G8: June | H8: July | I8: August | J8: September | K8: October | L8: November | M8: December | N8: January | O8: February | P8: March | Q8: April | R8: May | S8: June | T8: July | U8: August | V8: September | W8: October | X8: November | Y8: December | Z8: January | AA8: February | AB8: March | AC8: April | AD8: May | AE8: June | AF8: July | AG8: August | AH8: September | AI8: October | AJ8: November | AK8: December | AL8: January | AM8: February | AN8: March | AO8: April | AP8: May | AQ8: June | AR8: Jul | AS8: Aug | AT8: Sep | AU8: OCT | AV8: NOV | AW8: DEC | AX8: JAN | AY8: FEB | AZ8: MAR | BA8: APR | BB8: MAY | BC8: JUN | BD8: JUL | BE8: AUG | BF8: Total | BG8: Total | BH8: Total | BI8: Total | BJ8: Total | BK8: Total | BL8: Total | BM8: Total | BN8: Total | BO8: Total
A9: Profit and loss statement
A10: Gross margin
A11: Turnover
A12: 8400 - Turnover Airline | B12: -212427.24 | C12: -209910.73 | D12: -237563.67 | E12: -246794.29 | F12: -252583.71 | G12: -253028.07 | H12: -267357.32 | I12: -269824.48 | J12: -264391.88 | K12: -272661.31 | L12: -269216.39 | M12: -276889.25 | N12: -277258.01 | O12: -248239.08 | P12: -269843.96 | Q12: -271187.49 | R12: -284521.22 | S12: -281341.13 | T12: -294459.8 | U12: -304733.9 | V12: -297410.76 | W12: -305591.18 | X12: -300657.98 | Y12: -310981.73 | Z12: -307101.27 | AA12: -290242.86 | AB12: -313453.27 | AC12: -320579.06 | AD12: -329099.65 | AE12: -322160.9 | AF12: -341088.88 | AG12: -338087.72 | AH12: -337908.82 | AI12: -354813.3 | AJ12: -338698.12 | AK12: -341338.41 | AL12: -343853.07 | AM12: -310960.83 | AN12: -327130.77 | AO12: -333743.47 | AP12: -347838.97 | AQ12: -341992.87 | AR12: -330219.64 | AS12: -355833.33 | AT12: -390061.92 | AU12: -415418.59 | AV12: -390237.42 | AW12: -393057.44 | AX12: -338776.69 | AY12: -372164.38 | AZ12: -427667.19 | BA12: -383050.36 | BB12: -389957.34 | BC12: -400237.74 | BD12: -388638.18 | BE12: -395645.38 | BF12: =SUM(AX12:BE12) -> -3096137.3 | BG12: =SUM(AL12:AW12) -> -4280348.3 | BH12: =SUM(Z12:AK12) -> -3934572.3 | BI12: =SUM(N12:Y12) -> -3446226.2 | BJ12: =SUM(BA12:BE12) -> -1957529 | BK12: =SUM(AO12:AZ12) -> -4437011.9 | BL12: =SUM(AC12:AN12) -> -4005719.5 | BM12: =SUM(Q12:AB12) -> -3561682.6 | BN12: =SUM(E12:P12) -> -3168087.8 | BO12: =SUM(B12:D12) -> -659901.64
A13: 8401 - Turnover Airport | B13: -1250 | C13: -1250 | D13: -1250 | E13: -1250 | F13: -1250 | G13: -1250 | H13: -1250 | I13: -1250 | J13: -1479.45 | K13: -1528.77 | L13: -1479.45 | M13: -1528.77 | N13: -1528.77 | O13: -1380.82 | P13: -1528.77 | Q13: -1479.45 | R13: -1528.77 | S13: -1479.45 | T13: -1528.77 | U13: -1528.76 | V13: -1557.38 | W13: -1609.29 | X13: -1557.38 | Y13: -1609.29 | Z13: -1609.29 | AA13: -4476.77 | AB13: -4785.52 | AC13: -7085.7 | AD13: -7321.88 | AE13: -7085.7 | AF13: -10464.35 | AG13: -10464.34 | AH13: -10254.35 | AI13: -11406.74 | AJ13: -31778.52 | AK13: -15228.66 | AL13: -16727.73 | AM13: -16354.26 | AN13: -16736.43 | AO13: -13113.21 | AP13: -13550.32 | AQ13: -15900.52 | AR13: -15094.91 | AS13: -18067.49 | AT13: -21385.45 | AU13: -20809.38 | AV13: -19398.37 | AW13: -18855.91 | AX13: -19280.63 | AY13: -20464.36 | AZ13: -20177.1 | BA13: -21734.36 | BB13: -21027.36 | BC13: -25988.5 | BD13: -24017.98 | BE13: -21081.99 | BF13: =SUM(AX13:BE13) -> -173772.28 | BG13: =SUM(AL13:AW13) -> -205993.98 | BH13: =SUM(Z13:AK13) -> -121961.82 | BI13: =SUM(N13:Y13) -> -18316.9 | BJ13: =SUM(BA13:BE13) -> -113850.19 | BK13: =SUM(AO13:AZ13) -> -216097.65 | BL13: =SUM(AC13:AN13) -> -160908.66 | BM13: =SUM(Q13:AB13) -> -24750.12 | BN13: =SUM(E13:P13) -> -16704.8 | BO13: =SUM(B13:D13) -> -3750
A14: 8402 - Turnover Forwarder | B14: -43980.67 | C14: -39813.99 | D14: -43817.99 | E14: -39399.77 | F14: -45229.8 | G14: -48084.1 | H14: -45965.17 | I14: -47040.56 | J14: -45730.17 | K14: -50671.38 | L14: -49243.87 | M14: -47696.38 | N14: -49253.49 | O14: -48112.1 | P14: -53848.02 | Q14: -62216.51 | R14: -64716.2 | S14: -69475.77 | T14: -66092.95 | U14: -71573.98 | V14: -69478.96 | W14: -71975.54 | X14: -69653.77 | Y14: -75151.78 | Z14: -79783.88 | AA14: -74789.33 | AB14: -82348.7 | AC14: -76659.13 | AD14: -78034.9 | AE14: -84957.82 | AF14: -86055.81 | AG14: -86204.82 | AH14: -83423.99 | AI14: -94015.56 | AJ14: -94782.04 | AK14: -109973.56 | AL14: -121700.37 | AM14: -108473.19 | AN14: -121322.7 | AO14: -113455.67 | AP14: -112015.39 | AQ14: -125642.1 | AR14: -111480.63 | AS14: -118759.92 | AT14: -136045.4 | AU14: -126846.93 | AV14: -122927.72 | AW14: -131613.18 | AX14: -127494.89 | AY14: -95533.78 | AZ14: -121218.16 | BA14: -116152.23 | BB14: -130611.19 | BC14: -156785.28 | BD14: -120107.82 | BE14: -119115.56 | BF14: =SUM(AX14:BE14) -> -987018.91 | BG14: =SUM(AL14:AW14) -> -1450283.2 | BH14: =SUM(Z14:AK14) -> -1031029.5 | BI14: =SUM(N14:Y14) -> -771549.07 | BJ14: =SUM(BA14:BE14) -> -642772.08 | BK14: =SUM(AO14:AZ14) -> -1443033.8 | BL14: =SUM(AC14:AN14) -> -1145603.9 | BM14: =SUM(Q14:AB14) -> -857257.37 | BN14: =SUM(E14:P14) -> -570274.81 | BO14: =SUM(B14:D14) -> -127612.65
A15: 8403 - Turnover GSA | B15: -1178.08 | C15: -1178.08 | D15: -1305.48 | E15: -1301.37 | F15: -1714.98 | G15: -139.45 | H15: -1228.9 | I15: -1228.9 | J15: -1072.28 | K15: -1103.9 | L15: -1070.58 | M15: -1106.27 | N15: -5678.2 | O15: -3706.16 | P15: -4103.29 | Q15: -6196.56 | R15: -3878.29 | S15: -3937.55 | T15: -7008.05 | U15: -6232.23 | V15: -12845.95 | W15: -23390.47 | X15: -31187.83 | Y15: -32227.38 | Z15: -32795.63 | AA15: -31066.25 | AB15: -33463.22 | AC15: -38385.98 | AD15: -47118.62 | AE15: -45556.51 | AF15: -28681.02 | AG15: -28887.87 | AH15: -23817.74 | AI15: -29959.89 | AJ15: -32416.99 | AK15: -35923.6 | AL15: -37234.41 | AM15: -33562.09 | AN15: -36781.88 | AO15: -38365.62 | AP15: -35539.07 | AQ15: -34435.34 | AR15: -34085.52 | AS15: -33811.25 | AT15: -34093.18 | AU15: -38709.33 | AV15: -41724.9 | AW15: -54680.69 | AX15: -45399.56 | AY15: -43595.82 | AZ15: -45222.08 | BA15: -41778.39 | BB15: -44867.79 | BC15: -56485.84 | BD15: -54112.22 | BE15: -57691.48 | BF15: =SUM(AX15:BE15) -> -389153.18 | BG15: =SUM(AL15:AW15) -> -453023.28 | BH15: =SUM(Z15:AK15) -> -408073.32 | BI15: =SUM(N15:Y15) -> -140391.96 | BJ15: =SUM(BA15:BE15) -> -254935.72 | BK15: =SUM(AO15:AZ15) -> -479662.36 | BL15: =SUM(AC15:AN15) -> -418326.6 | BM15: =SUM(Q15:AB15) -> -224229.41 | BN15: =SUM(E15:P15) -> -23454.28 | BO15: =SUM(B15:D15) -> -3661.64
A16: 8404 - Turnover Shipper | J16: -805.48 | K16: -832.33 | L16: -805.48 | M16: -832.33 | N16: -832.33 | O16: -751.78 | P16: -832.33 | Q16: -1952.13 | R16: -2017.2 | S16: -1952.13 | T16: -2017.2 | U16: -2017.19 | V16: -1146.65 | W16: -1184.87 | X16: -1146.65 | Y16: -3861.06 | Z16: -3861.06 | AA16: -3611.95 | AB16: -3861.06 | AC16: -5331.96 | AD16: -5509.7 | AE16: -10186.29 | AF16: -10525.84 | AG16: -10525.84 | AH16: -12487.66 | AI16: -12903.92 | AJ16: -14131.5 | AK16: -11890.46 | AL16: -11401.75 | AM16: -10298.37 | AN16: -16709.97 | AO16: -21543.98 | AP16: -22262.09 | AQ16: -23023.43 | AR16: -23790.87 | AS16: -23790.9 | AT16: -20614.21 | AU16: -29881.85 | AV16: -33710.84 | AW16: -33536.49 | AX16: -28631.22 | AY16: -25860.44 | AZ16: -28705.26 | BA16: -27779.28 | BB16: -28705.24 | BC16: -27823.66 | BD16: -31086.74 | BE16: -35749.89 | BF16: =SUM(AX16:BE16) -> -234341.73 | BG16: =SUM(AL16:AW16) -> -270564.75 | BH16: =SUM(Z16:AK16) -> -104827.24 | BI16: =SUM(N16:Y16) -> -19711.52 | BJ16: =SUM(BA16:BE16) -> -151144.81 | BK16: =SUM(AO16:AZ16) -> -315351.58 | BL16: =SUM(AC16:AN16) -> -131903.26 | BM16: =SUM(Q16:AB16) -> -28629.15 | BN16: =SUM(E16:P16) -> -5692.06 | BO16: =SUM(B16:D16) -> 0
A17: 8405 - Turnover Other | AO17: 0 | AP17: -439.92 | AQ17: -425.73 | AR17: -4807.7 | AS17: -7136.47 | AT17: -8762.2 | AU17: -9054.28 | AV17: -8762.2 | AW17: -9054.28 | AX17: -10461.61 | AY17: -9449.2 | AZ17: -10461.61 | BA17: -11028.23 | BB17: -11408.63 | BC17: -11040.62 | BD17: -11508.97 | BE17: -11508.93 | BF17: =SUM(AX17:BE17) -> -86867.8 | BG17: =SUM(AL17:AW17) -> -48442.78 | BH17: =SUM(Z17:AK17) -> 0 | BJ17: =SUM(BA17:BE17) -> -56495.38 | BK17: =SUM(AO17:AZ17) -> -78815.2 | BL17: =SUM(AC17:AN17) -> 0
A18: 8500 - Turnover adjustments prior financial year | D18: 96.29 | E18: -0.01 | F18: -10000.01 | G18: -4596.27 | K18: -6875 | Q18: -12488.75 | R18: -40291.67 | W18: 123.29 | X18: -1770.83 | Y18: -3500 | AC18: 7708.2 | AD18: -10916.66 | AE18: 0 | AF18: -7732.5 | AG18: 0 | AH18: -15249.32 | AI18: 3188.78 | AJ18: 0 | AK18: -11095 | AL18: 0 | AM18: 0 | AN18: 0 | AO18: -14042.64 | AP18: -13576.78 | AQ18: -8708 | AR18: 0 | AS18: -6542 | AT18: 188 | AU18: -15571.5 | AV18: -5000 | AW18: -1882 | AX18: 0 | AY18: -1818.18 | AZ18: 0 | BA18: -16319.24 | BB18: -22895.35 | BC18: -951.22 | BD18: 0 | BE18: 0 | BF18: =SUM(AX18:BE18) -> -41983.99 | BG18: =SUM(AL18:AW18) -> -65134.92 | BH18: =SUM(Z18:AK18) -> -34096.5 | BI18: =SUM(N18:Y18) -> -57927.96 | BJ18: =SUM(BA18:BE18) -> -40165.81 | BK18: =SUM(AO18:AZ18) -> -66953.1 | BL18: =SUM(AC18:AN18) -> -34096.5 | BM18: =SUM(Q18:AB18) -> -57927.96 | BN18: =SUM(E18:P18) -> -21471.29 | BO18: =SUM(B18:D18) -> 96.29
A19: Total: Turnover | B19: -258835.99 | C19: -252152.8 | D19: -283840.85 | E19: -288745.44 | F19: -310778.5 | G19: -307097.89 | H19: -315801.39 | I19: -319343.94 | J19: -313479.26 | K19: -333672.69 | L19: -321815.77 | M19: -328053 | N19: -334550.8 | O19: -302189.94 | P19: -330156.37 | Q19: =SUM(Q12:Q18) -> -355520.89 | R19: =SUM(R12:R18) -> -396953.35 | S19: =SUM(S12:S18) -> -358186.03 | T19: =SUM(T12:T18) -> -371106.77 | U19: =SUM(U12:U18) -> -386086.06 | V19: =SUM(V12:V18) -> -382439.7 | W19: =SUM(W12:W18) -> -403628.06 | X19: =SUM(X12:X18) -> -405974.44 | ... BE19: =SUM(BE12:BE18) -> -640793.23 | BF19: =SUM(AX19:BE19) -> -5009275.1 | BG19: =SUM(AL19:AW19) -> -6773791.2 | BH19: =SUM(Z19:AK19) -> -5634560.7 | BI19: =SUM(N19:Y19) -> -4454123.7 | BJ19: =SUM(BA19:BE19) -> -3216893 | BK19: =SUM(AO19:AZ19) -> -7036925.6 | BL19: =SUM(AC19:AN19) -> -5896558.4 | BM19: =SUM(Q19:AB19) -> -4754476.6 | BN19: =SUM(E19:P19) -> -3805685 | BO19: =SUM(B19:D19) -> -794829.64
A20: Cost of sales | AO20: 0 | AP20: 0 | AQ20: 0 | AR20: 0 | AS20: 0 | AT20: 0 | AU20: 0 | AV20: 0 | AW20: 0 | AX20: 0 | AY20: 0
A21: 7300 - Licensing fees | B21: 2485.56 | C21: 2485.56 | D21: 2485.56 | E21: 2696.44 | F21: 2591.4 | G21: 2588.59 | H21: 1692.73 | I21: 1301.38 | J21: 2021.64 | K21: 4256.76 | L21: 4283.55 | M21: 4500.32 | N21: 3955.2 | O21: 5371.92 | P21: 5080.23 | Q21: 5047.62 | R21: 5654.3 | S21: 4938.7 | T21: 7019.09 | U21: 9676.97 | V21: 7319.91 | W21: 9276.64 | X21: 6103.61 | Y21: 5275.25 | Z21: 5617.87 | AA21: 7488.15 | AB21: 7142.85 | AC21: 7155.9 | AD21: 6655.11 | AE21: 36583.34 | AF21: 25780.1 | AG21: 5822.75 | AH21: 6136.45 | AI21: 55014.13 | AJ21: 1860.7 | AK21: 1929.01 | AL21: 1934.88 | AM21: 2029.5 | AN21: 1801.75 | AO21: 539.19 | AP21: 486.38 | AQ21: 805.44 | AR21: 2615.38 | AS21: 2744.64 | AT21: 2810.74 | AU21: 4828.72 | AV21: 6554.09 | AW21: 6772.57 | AX21: 32072.6 | AY21: 16499.66 | AZ21: 14980 | BA21: 14575.96 | BB21: 14685.17 | BC21: -361.53 | BD21: 213.46 | BE21: -6629.36 | BF21: =SUM(AX21:BE21) -> 86035.96 | BG21: =SUM(AL21:AW21) -> 33923.28 | BH21: =SUM(Z21:AK21) -> 167186.36 | BI21: =SUM(N21:Y21) -> 74719.44 | BJ21: =SUM(BA21:BE21) -> 22483.7 | BK21: =SUM(AO21:AZ21) -> 91709.41 | BL21: =SUM(AC21:AN21) -> 152703.62 | BM21: =SUM(Q21:AB21) -> 80560.96 | BN21: =SUM(E21:P21) -> 40340.16 | BO21: =SUM(B21:D21) -> 7456.68
A22: Total: Cost of sales | B22: 2485.56 | C22: 2485.56 | D22: 2485.56 | E22: 2696.44 | F22: 2591.4 | G22: 2588.59 | H22: 1692.73 | I22: 1301.38 | J22: 2021.64 | K22: 4256.76 | L22: 4283.55 | M22: 4500.32 | N22: 3955.2 | O22: 5371.92 | P22: 5080.23 | Q22: =SUM(Q21) -> 5047.62 | R22: =SUM(R21) -> 5654.3 | S22: =SUM(S21) -> 4938.7 | T22: =SUM(T21) -> 7019.09 | U22: =SUM(U21) -> 9676.97 | V22: =SUM(V21) -> 7319.91 | W22: =SUM(W21) -> 9276.64 | X22: =SUM(X21) -> 6103.61 | ... BE22: =SUM(BE21) -> -6629.36 | BF22: =SUM(AX22:BE22) -> 86035.96 | BG22: =SUM(AL22:AW22) -> 33923.28 | BH22: =SUM(Z22:AK22) -> 167186.36 | BI22: =SUM(N22:Y22) -> 74719.44 | BJ22: =SUM(BA22:BE22) -> 22483.7 | BK22: =SUM(AO22:AZ22) -> 91709.41 | BL22: =SUM(AC22:AN22) -> 152703.62 | BM22: =SUM(Q22:AB22) -> 80560.96 | BN22: =SUM(E22:P22) -> 40340.16 | BO22: =SUM(B22:D22) -> 7456.68 | BP22: COGS
A23: Total: Gross margin | B23: -256350.43 | C23: -249667.24 | D23: -281355.29 | E23: -286049 | F23: -308187.1 | G23: -304509.3 | H23: -314108.66 | I23: -318042.56 | J23: -311457.62 | K23: -329415.93 | L23: -317532.22 | M23: -323552.68 | N23: -330595.6 | O23: -296818.02 | P23: -325076.14 | Q23: =SUM(Q19+Q22) -> -350473.27 | R23: =SUM(R19+R22) -> -391299.05 | S23: =SUM(S19+S22) -> -353247.33 | T23: =SUM(T19+T22) -> -364087.68 | U23: =SUM(U19+U22) -> -376409.09 | V23: =SUM(V19+V22) -> -375119.79 | W23: =SUM(W19+W22) -> -394351.42 | X23: =SUM(X19+X22) -> -399870.83 | ... BE23: =SUM(BE19+BE22) -> -647422.59 | BF23: =SUM(AX23:BE23) -> -4923239.2 | BG23: =SUM(AL23:AW23) -> -6739868 | BH23: =SUM(Z23:AK23) -> -5467374.3 | BI23: =SUM(N23:Y23) -> -4379404.2 | BJ23: =SUM(BA23:BE23) -> -3194409.3 | BK23: =SUM(AO23:AZ23) -> -6945216.2 | BL23: =SUM(AC23:AN23) -> -5743854.8 | BM23: =SUM(Q23:AB23) -> -4673915.6 | BN23: =SUM(N23:Y23) -> -4379404.2 | BO23: =SUM(B23:D23) -> -787372.96
A24: Operating costs
A25: Personnel Expenses
A26: 4000 - Gross salary | B26: 28519.01 | C26: 28519.01 | D26: 28519.01 | E26: 28820.08 | F26: 28991.51 | G26: 28991.51 | H26: 32516.51 | I26: 32516.51 | J26: 38289.29 | K26: 39241.51 | L26: 39054.01 | M26: 39054.01 | N26: 43754.01 | O26: 46056.48 | P26: 44607.85 | Q26: 39759.99 | R26: 40177.99 | S26: 40627.99 | T26: 40909.99 | U26: 42866.51 | V26: 46303.53 | W26: 46330.74 | X26: 46330.74 | Y26: 49830.74 | Z26: 57004.59 | AA26: 57178.5 | AB26: 57178.5 | AC26: 61178.5 | AD26: 62127.5 | AE26: 70460.5 | AF26: 70460.5 | AG26: 69446.38 | AH26: 77238.38 | AI26: 78423.38 | AJ26: 74814.88 | AK26: 74814.88 | AL26: 82674.94 | AM26: 86782.18 | AN26: 81010.67 | AO26: 90056.79 | AP26: 86782.18 | AQ26: 89284.94 | AR26: 95960.18 | AS26: 96670.02 | AT26: 89043.18 | AU26: 102081.18 | AV26: 104414.66 | AW26: 104414.77 | AX26: 102341.06 | AY26: 103729.38 | AZ26: 109215.14 | BA26: 108764.98 | BB26: 108764.98 | BC26: 108764.98 | BD26: 104603.36 | BE26: 110330.54 | BF26: =SUM(AX26:BE26) -> 856514.42 | BG26: =SUM(AL26:AW26) -> 1109175.7 | BH26: =SUM(Z26:AK26) -> 810326.49 | BI26: =SUM(N26:Y26) -> 527556.56 | BJ26: =SUM(BA26:BE26) -> 541228.84 | BK26: =SUM(AO26:AZ26) -> 1173993.5 | BL26: =SUM(AC26:AN26) -> 889432.69 | BM26: =SUM(Q26:AB26) -> 564499.81 | BN26: =SUM(E26:P26) -> 441893.28 | BO26: =SUM(B26:D26) -> 85557.03
A27: 4002 - Bonus pay | D27: 0 | G27: 46739 | P27: 16000 | S27: 71644 | AC27: 0 | AD27: 0 | AE27: 0 | AF27: 0 | AG27: 97197 | AH27: 0 | AI27: 0 | AJ27: 2000 | AK27: 0 | AL27: 0 | AM27: 0 | AN27: 0 | AO27: 0 | AP27: 0 | AQ27: 159315 | AR27: 0 | AS27: 0 | AT27: 0 | AU27: 0 | AV27: 4758 | AW27: 0 | AX27: 0 | AY27: 0 | AZ27: 0 | BA27: 0 | BB27: 0 | BC27: 20810 | BD27: 15760 | BE27: 21115 | BF27: =SUM(AX27:BE27) -> 57685 | BG27: =SUM(AL27:AW27) -> 164073 | BH27: =SUM(Z27:AK27) -> 99197 | BI27: =SUM(N27:Y27) -> 87644 | BJ27: =SUM(BA27:BE27) -> 57685 | BK27: =SUM(AO27:AZ27) -> 164073 | BL27: =SUM(AC27:AN27) -> 99197 | BM27: =SUM(Q27:AB27) -> 71644 | BN27: =SUM(E27:P27) -> 62739 | BO27: =SUM(B27:D27) -> 0
A28: 4004 - Temporary staff | AC28: 0 | AD28: 0 | AE28: 3075 | AF28: 2025 | AG28: 0 | AH28: 1725 | AI28: 7050 | AJ28: 5775 | AK28: 2625 | AL28: 5250 | AM28: 0 | AN28: 0 | AO28: 3525 | AP28: 0 | AQ28: 3750 | AR28: 3112.5 | AS28: 3112.5 | AT28: 9525 | AU28: 8800 | AV28: 500 | AW28: 7950 | AX28: 7000 | AY28: -7000 | AZ28: 0 | BA28: 0 | BF28: =SUM(AX28:BE28) -> 0 | BG28: =SUM(AL28:AW28) -> 45525 | BH28: =SUM(Z28:AK28) -> 22275 | BI28: =SUM(N28:Y28) -> 0 | BJ28: =SUM(BA28:BE28) -> 0 | BK28: =SUM(AO28:AZ28) -> 40275 | BL28: =SUM(AC28:AN28) -> 27525
A29: 4006 - Pension premiums | B29: 2162.33 | C29: 2150.08 | D29: 2650.08 | E29: 2150.08 | F29: 2116.75 | G29: 2150.08 | H29: 2150.08 | I29: 2150.08 | J29: 2153.51 | K29: 2163.46 | L29: 4645.67 | M29: 3748.88 | N29: 3585.7 | O29: -500 | P29: 3167.88 | Q29: 6980.16 | R29: 4031.69 | S29: 3000 | T29: 3383.85 | U29: 3000 | V29: 3173.17 | W29: 3120.39 | X29: 6574.45 | Y29: 11299.45 | Z29: 6109.28 | AA29: 5610.89 | AB29: 7673.98 | AC29: 6528.67 | AD29: 7292.73 | AE29: 7207.26 | AF29: 8978 | AG29: 8018.49 | AH29: 17343.86 | AI29: 8421.93 | AJ29: 7397.77 | AK29: 7261.31 | AL29: 9416.01 | AM29: 6114.23 | AN29: 18925.47 | AO29: -1302.99 | AP29: -500 | AQ29: 18122.48 | AR29: -500 | AS29: 10989.73 | AT29: 22012.68 | AU29: 10756.34 | AV29: 18756.38 | AW29: 18750 | AX29: 8887.09 | AY29: 13117.15 | AZ29: 12316.2 | BA29: 12029.83 | BB29: 12029.83 | BC29: 12000 | BD29: 12377.19 | BE29: 12148.28 | BF29: =SUM(AX29:BE29) -> 94905.57 | BG29: =SUM(AL29:AW29) -> 131540.33 | BH29: =SUM(Z29:AK29) -> 97844.17 | BI29: =SUM(N29:Y29) -> 50816.74 | BJ29: =SUM(BA29:BE29) -> 60585.13 | BK29: =SUM(AO29:AZ29) -> 131405.06 | BL29: =SUM(AC29:AN29) -> 112905.73 | BM29: =SUM(Q29:AB29) -> 63957.31 | BN29: =SUM(E29:P29) -> 29682.17 | BO29: =SUM(B29:D29) -> 6962.49
A30: 4015 - Holiday allowance | B30: 2281.52 | C30: 2281.52 | D30: 2281.52 | E30: 2305.61 | F30: 2319.32 | G30: 2319.32 | H30: 2601.32 | I30: 2601.32 | J30: 3063.14 | K30: 3139.32 | L30: 3124.32 | M30: 3124.32 | N30: 3500.32 | O30: 3684.52 | P30: 3568.63 | Q30: 3180.8 | R30: 3214.24 | S30: 3250.24 | T30: 3272.8 | U30: 3429.32 | V30: 3704.28 | W30: 3706.46 | X30: 3706.46 | Y30: 3986.46 | Z30: 4400.37 | AA30: 4574.28 | AB30: 4574.28 | AC30: 4894.28 | AD30: 4970.2 | AE30: 5636.84 | AF30: 5636.84 | AG30: 5555.71 | AH30: 6179.07 | AI30: 2940.67 | AJ30: 5985.19 | AK30: 5985.19 | AL30: 6359.21 | AM30: 6942.58 | AN30: 6942.58 | AO30: 6942.58 | AP30: 6942.58 | AQ30: 7142.8 | AR30: 7676.82 | AS30: 7733.6 | AT30: 8547.05 | AU30: 8703.57 | AV30: 8890.25 | AW30: 8782.21 | AX30: 9249.03 | AY30: 9249.03 | AZ30: 9285.04 | BA30: 9249.03 | BB30: 9249.03 | BC30: 9249.03 | BD30: 9473.11 | BE30: 9384.47 | BF30: =SUM(AX30:BE30) -> 74387.77 | BG30: =SUM(AL30:AW30) -> 91605.83 | BH30: =SUM(Z30:AK30) -> 61332.92 | BI30: =SUM(N30:Y30) -> 42204.53 | BJ30: =SUM(BA30:BE30) -> 46604.67 | BK30: =SUM(AO30:AZ30) -> 99144.56 | BL30: =SUM(AC30:AN30) -> 68028.36 | BM30: =SUM(Q30:AB30) -> 44999.99 | BN30: =SUM(E30:P30) -> 35351.46 | BO30: =SUM(B30:D30) -> 6844.56
A31: 4016 - Work from home allowance | AC31: 0 | AD31: 0 | AE31: 0 | AF31: 0 | AG31: 0 | AH31: 0 | AI31: 0 | AJ31: 0 | AK31: 2800 | AL31: 2800 | AM31: 0 | AN31: 0 | AO31: 0 | AP31: 0 | AQ31: 0 | AR31: 0 | AS31: 0 | AT31: 0 | AU31: 0 | AV31: 0 | AW31: 0 | AX31: 0 | AY31: 0 | AZ31: 0 | BA31: 0 | BF31: =SUM(AX31:BE31) -> 0 | BG31: =SUM(AL31:AW31) -> 2800 | BH31: =SUM(Z31:AK31) -> 2800 | BI31: =SUM(N31:Y31) -> 0 | BJ31: =SUM(BA31:BE31) -> 0 | BK31: =SUM(AO31:AZ31) -> 0 | BL31: =SUM(AC31:AN31) -> 5600 | BM31: =SUM(Q31:AB31) -> 0 | BN31: =SUM(E31:P31) -> 0 | BO31: =SUM(B31:D31) -> 0
A32: 4017 - Employee Gifts | AM32: 0 | AN32: 0 | AO32: 0 | AP32: 0 | AQ32: 0 | AR32: 0 | AS32: 0 | AT32: 0 | AU32: 0 | AV32: 0 | AW32: 3049.52 | AX32: 0 | AY32: 0 | AZ32: 0 | BA32: 0 | BF32: =SUM(AX32:BE32) -> 0 | BG32: =SUM(AL32:AW32) -> 3049.52 | BH32: =SUM(Z32:AK32) -> 0 | BJ32: =SUM(BA32:BE32) -> 0 | BK32: =SUM(AO32:AZ32) -> 3049.52 | BL32: =SUM(AC32:AN32) -> 0
A33: 4041 - Social insurance premiums | B33: 5264.81 | C33: 5264.81 | D33: 5264.81 | E33: 5288.69 | F33: 4878.65 | G33: 7218.42 | H33: 5575.38 | I33: 5575.38 | J33: 6631.67 | K33: 6692.53 | L33: 6662.1 | M33: 7708.16 | N33: 8004.33 | O33: 8198.03 | P33: 8052.55 | Q33: 7345.49 | R33: 7191.58 | S33: 11591.22 | T33: 7594.72 | U33: 8012.44 | V33: 8499.19 | W33: 8496.48 | X33: 8496.48 | Y33: 11807.84 | Z33: 10356.82 | AA33: 10823.79 | AB33: 10823.79 | AC33: 9449.19 | AD33: 11124.54 | AE33: 12406.66 | AF33: 10572.09 | AG33: 19763.04 | AH33: 13564.39 | AI33: 13818.92 | AJ33: 13738.45 | AK33: 18827.09 | AL33: 13242.98 | AM33: 15680.76 | AN33: 15680.76 | AO33: 15467.81 | AP33: 15467.81 | AQ33: 28873.8 | AR33: 18031.72 | AS33: 17780.98 | AT33: 18745.18 | AU33: 19170.91 | AV33: 19548.75 | AW33: 26345.73 | AX33: 19665.7 | AY33: 19216.15 | AZ33: 19257.03 | BA33: 19016.05 | BB33: 19016.05 | BC33: 19016.05 | BD33: 38953.96 | BE33: 19562.45 | BF33: =SUM(AX33:BE33) -> 173703.44 | BG33: =SUM(AL33:AW33) -> 224037.19 | BH33: =SUM(Z33:AK33) -> 155268.77 | BI33: =SUM(N33:Y33) -> 103290.35 | BJ33: =SUM(BA33:BE33) -> 115564.56 | BK33: =SUM(AO33:AZ33) -> 237571.57 | BL33: =SUM(AC33:AN33) -> 167868.87 | BM33: =SUM(Q33:AB33) -> 111039.84 | BN33: =SUM(E33:P33) -> 80485.89 | BO33: =SUM(B33:D33) -> 15794.43
A34: 4050 - Study and training expenses | O34: 5000 | S34: 10500 | T34: 1210 | AC34: 0 | AD34: 0 | AE34: 0 | AF34: 0 | AG34: 0 | AH34: 0 | AI34: 0 | AJ34: 0 | AK34: 0 | AL34: 0 | AM34: 0 | AN34: 0 | AO34: 0 | AP34: 0 | AQ34: 0 | AR34: 3652.07 | AS34: 4079.47 | AT34: 20432.9 | AU34: -23888 | AV34: 0 | AW34: 3219.99 | AX34: 1914.89 | AY34: 243.2 | AZ34: 11540.47 | BA34: 753.08 | BB34: 5813.69 | BC34: 12148.38 | BD34: 1778.97 | BE34: 2653.98 | BF34: =SUM(AX34:BE34) -> 36846.66 | BG34: =SUM(AL34:AW34) -> 7496.43 | BI34: =SUM(N34:Y34) -> 16710 | BJ34: =SUM(BA34:BE34) -> 23148.1 | BK34: =SUM(AO34:AZ34) -> 21194.99 | BL34: =SUM(AC34:AN34) -> 0 | BM34: =SUM(Q34:AB34) -> 11710 | BN34: =SUM(E34:P34) -> 5000 | BO34: =SUM(B34:D34) -> 0
A35: 4060 - Consumptions personnel discretionary scope (vrije ruimte) | AC35: 0 | AD35: 302.17 | AE35: 157.07 | AF35: 1262.32 | AG35: 391.83 | AH35: 501.2 | AI35: 340.1 | AJ35: 639.85 | AK35: 523.19 | AL35: 2735.37 | AM35: 618.73 | AN35: 614.78 | AO35: 772.28 | AP35: 667.3 | AQ35: 345.21 | AR35: 680.62 | AS35: 5851.72 | AT35: 1037.94 | AU35: 1304.46 | AV35: 707.44 | AW35: 5982.46 | AX35: 588.73 | AY35: 628.25 | AZ35: 860.38 | BA35: 418.08 | BB35: 735.83 | BC35: 201.59 | BD35: 300.44 | BE35: 496.11 | BF35: =SUM(AX35:BE35) -> 4229.41 | BG35: =SUM(AL35:AW35) -> 21318.31 | BH35: =SUM(Z35:AK35) -> 4117.73 | BJ35: =SUM(BA35:BE35) -> 2152.05 | BK35: =SUM(AO35:AZ35) -> 19426.79 | BL35: =SUM(AC35:AN35) -> 8086.61
A36: 4081 - Social insurance premiums holiday allowance | B36: 456.3 | C36: 456.3 | D36: 456.3 | E36: 461.12 | F36: 461.12 | G36: 461.12 | H36: 461.12 | I36: 461.12 | J36: 461.12 | K36: 461.12 | L36: 461.12 | M36: 461.12 | N36: 461.12 | O36: 461.12 | P36: 461.12 | Q36: 461.12 | R36: 461.12 | S36: 461.12 | T36: 461.12 | U36: 461.12 | V36: 461.12 | W36: 461.12 | X36: 461.12 | Y36: 461.12 | Z36: 461.12 | AA36: 461.12 | AB36: -9264.86 | AC36: 978.86 | AD36: 994.04 | AE36: 1127.37 | AF36: 1127.37 | AG36: 1111.14 | AH36: 1235.82 | AI36: 1254.78 | AJ36: 1197.04 | AK36: 1197.04 | AL36: 1255.14 | AM36: 1456.18 | AN36: 1388.52 | AO36: 1388.51 | AP36: 1388.51 | AQ36: 1428 | AR36: 1535.36 | AS36: 1546.72 | AT36: 1709.41 | AU36: 1709.41 | AV36: 1778.05 | AW36: 1778.05 | AX36: 1849.81 | AY36: 1849.81 | AZ36: 1849.81 | BA36: 1849.81 | BB36: 1849.81 | BC36: 1849.81 | BD36: 1876.89 | BE36: 1876.89 | BF36: =SUM(AX36:BE36) -> 14852.64 | BG36: =SUM(AL36:AW36) -> 18361.86 | BH36: =SUM(Z36:AK36) -> 1880.84 | BI36: =SUM(N36:Y36) -> 5533.44 | BJ36: =SUM(BA36:BE36) -> 9303.21 | BK36: =SUM(AO36:AZ36) -> 19811.45 | BL36: =SUM(AC36:AN36) -> 14323.3 | BM36: =SUM(Q36:AB36) -> -4192.54 | BN36: =SUM(E36:P36) -> 5533.44 | BO36: =SUM(B36:D36) -> 1368.9
A37: 4082 - Management Fee Shanwick B.V. | D37: 0 | F37: 31041.33 | G37: 31041.33 | H37: 31041.33 | I37: 31041.33 | J37: 31041.33 | K37: 31041.33 | L37: 31041.33 | M37: 31041.33 | N37: 31041.33 | O37: 31041.33 | P37: 31041.33 | Q37: 31041.33 | R37: 31041.33 | S37: 31041.33 | T37: 31041.33 | U37: 31041.33 | V37: 31041.33 | W37: 31041.33 | X37: 31041.33 | Y37: 31041.33 | Z37: 31041.33 | AA37: 31041.33 | AB37: 31041.33 | AC37: 31041.33 | AD37: 31041.33 | AE37: 31041.33 | AF37: 31041.33 | AG37: 31041.33 | AH37: 31041.33 | AI37: 31041.33 | AJ37: 31041.33 | AK37: 31041.33 | AL37: 31041.33 | AM37: 31041.33 | AN37: 31041.33 | AO37: 31041.33 | AP37: 33009.33 | AQ37: 31533.33 | AR37: 31533.33 | AS37: 31533.33 | AT37: 31533.33 | AU37: 31533.33 | AV37: 31533.33 | AW37: 31533.33 | AX37: 31533.33 | AY37: 31533.33 | AZ37: 31533.33 | BA37: 37731 | BB37: 37731 | BC37: 37731 | BD37: 37731 | BE37: 37731 | BF37: =SUM(AX37:BE37) -> 283254.99 | BG37: =SUM(AL37:AW37) -> 377907.96 | BH37: =SUM(Z37:AK37) -> 372495.96 | BI37: =SUM(N37:Y37) -> 372495.96 | BJ37: =SUM(BA37:BE37) -> 188655 | BK37: =SUM(AO37:AZ37) -> 379383.96 | BL37: =SUM(AC37:AN37) -> 372495.96 | BM37: =SUM(Q37:AB37) -> 372495.96 | BN37: =SUM(E37:P37) -> 341454.63 | BO37: =SUM(B37:D37) -> 0
A38: 4085 - Holiday leave | B38: 2000.98 | C38: 2000.98 | D38: 2000.99 | F38: 4001.97 | G38: 2001.98 | H38: 2001.98 | I38: 2001.98 | J38: 2001.98 | K38: 2001.98 | L38: 2001.98 | M38: 2001.98 | N38: 2001.98 | O38: 2001.98 | P38: 2001.98 | Q38: 2001.98 | R38: 2001.98 | S38: 2001.98 | T38: 2001.98 | U38: 2001.98 | V38: 2001.98 | W38: 2001.98 | X38: 2001.98 | Y38: 2001.98 | Z38: 2001.98 | AA38: 2001.98 | AB38: 2001.98 | AC38: 2001.98 | AD38: 2001.98 | AE38: 2001.98 | AF38: 2001.98 | AG38: 2001.98 | AH38: 2001.98 | AI38: 2001.98 | AJ38: 2001.98 | AK38: 2001.98 | AL38: 2001.98 | AM38: 2001.98 | AN38: 2001.98 | AO38: 2001.98 | AP38: 2001.98 | AQ38: 2001.98 | AR38: 2001.98 | AS38: 2001.98 | AT38: 2001.98 | AU38: 2001.98 | AV38: 2001.98 | AW38: 2001.98 | AX38: 2001.98 | AY38: 2001.98 | AZ38: 2001.98 | BA38: 2001.98 | BB38: 2001.98 | BC38: 2001.98 | BD38: 2001.98 | BE38: 2001.98 | BF38: =SUM(AX38:BE38) -> 16015.84 | BG38: =SUM(AL38:AW38) -> 24023.76 | BH38: =SUM(Z38:AK38) -> 24023.76 | BI38: =SUM(N38:Y38) -> 24023.76 | BJ38: =SUM(BA38:BE38) -> 10009.9 | BK38: =SUM(AO38:AZ38) -> 24023.76 | BL38: =SUM(AC38:AN38) -> 24023.76 | BM38: =SUM(Q38:AB38) -> 24023.76 | BN38: =SUM(E38:P38) -> 24021.77 | BO38: =SUM(B38:D38) -> 6002.95
A39: 4086 - Management Fee Decision Company B.V. | B39: 14370 | C39: 14508 | D39: 14508 | E39: 14508 | AC39: 0 | AD39: 0 | AE39: 0 | AF39: 0 | AG39: 0 | AH39: 0 | AI39: 0 | AJ39: 0 | AK39: 0 | AL39: 0 | AM39: 0 | AN39: 0 | AO39: 0 | AP39: 0 | AQ39: 0 | AR39: 0 | AS39: 0 | AT39: 0 | AU39: 0 | AV39: 0 | AW39: 0 | AX39: 0 | AY39: 0 | AZ39: 0 | BA39: 0 | BB39: 0 | BC39: 0 | BD39: 0 | BE39: 0 | BF39: =SUM(AX39:BE39) -> 0 | BG39: =SUM(AL39:AW39) -> 0 | BI39: =SUM(N39:Y39) -> 0 | BJ39: =SUM(BA39:BE39) -> 0 | BK39: =SUM(AO39:AZ39) -> 0 | BL39: =SUM(AC39:AN39) -> 0 | BM39: =SUM(Q39:AB39) -> 0 | BN39: =SUM(E39:P39) -> 14508 | BO39: =SUM(B39:D39) -> 43386
A40: 4087 - Management Fee Ubi Concordia B.V. | B40: 15990 | C40: 16533.33 | D40: 16533.33 | E40: 16533.33 | AC40: 0 | AD40: 0 | AE40: 0 | AF40: 0 | AG40: 0 | AH40: 0 | AI40: 0 | AJ40: 0 | AK40: 0 | AL40: 0 | AM40: 0 | AN40: 0 | AO40: 0 | AP40: 0 | AQ40: 0 | AR40: 0 | AS40: 0 | AT40: 0 | AU40: 0 | AV40: 0 | AW40: 0 | AX40: 0 | AY40: 0 | AZ40: 0 | BA40: 0 | BF40: =SUM(AX40:BE40) -> 0 | BG40: =SUM(AL40:AW40) -> 0 | BI40: =SUM(N40:Y40) -> 0 | BJ40: =SUM(BA40:BE40) -> 0 | BK40: =SUM(AO40:AZ40) -> 0 | BL40: =SUM(AC40:AN40) -> 0 | BM40: =SUM(Q40:AB40) -> 0 | BN40: =SUM(E40:P40) -> 16533.33 | BO40: =SUM(B40:D40) -> 49056.66
A41: 4090 - Other personnel exp. discretionary scope (vrije ruimte) | L41: 1454.5 | M41: 2132.54 | Z41: 1542.17 | AC41: 0 | AD41: 0 | AE41: 0 | AF41: 0 | AG41: 0 | AH41: 0 | AI41: 0 | AJ41: 0 | AK41: 0 | AL41: 0 | AM41: 0 | AN41: 0 | AO41: 0 | AP41: 0 | AQ41: 0 | AR41: 0 | AS41: 0 | AT41: 0 | AU41: 0 | AV41: 0 | AW41: 0 | AX41: 0 | AY41: 0 | AZ41: 0 | BA41: 0 | BF41: =SUM(AX41:BE41) -> 0 | BG41: =SUM(AL41:AW41) -> 0 | BI41: =SUM(N41:Y41) -> 0 | BJ41: =SUM(BA41:BE41) -> 0 | BK41: =SUM(AO41:AZ41) -> 0 | BL41: =SUM(AC41:AN41) -> 0 | BM41: =SUM(Q41:AB41) -> 1542.17 | BN41: =SUM(E41:P41) -> 3587.04 | BO41: =SUM(B41:D41) -> 0
A42: 4092 - Travel and subsistence expenses | C42: 27 | D42: 0 | E42: 523.37 | F42: 34 | G42: 382.4 | H42: 1065.03 | I42: 3493.08 | J42: 2025.8 | K42: 5713.65 | L42: 12153.25 | M42: 5858.36 | N42: 2807.95 | O42: 696.69 | P42: 5059.07 | Q42: 2551.19 | R42: 12228.2 | S42: 17070.91 | T42: 6941.82 | U42: -8116.77 | V42: -22.24 | W42: 1535.56 | X42: 3820.51 | Y42: 2316.33 | Z42: 1318.77 | AA42: 6349.18 | AB42: 3168.19 | AC42: 6317.26 | AD42: 757.61 | AE42: 7921.72 | AF42: 14264.9 | AG42: 4173.53 | AH42: 1548.73 | AI42: 12924.98 | AJ42: 5397.8 | AK42: 3826.67 | AL42: 2952.7 | AM42: 4543.71 | AN42: 5783.78 | AO42: 3030.98 | AP42: 11007.06 | AQ42: 1484.67 | AR42: 1389.41 | AS42: 6547.01 | AT42: 3986.18 | AU42: 8304.17 | AV42: 1889.71 | AW42: 4187.6 | AX42: 6757.46 | AY42: 5232.55 | AZ42: 3108.28 | BA42: 2586.97 | BB42: 6116.7 | BC42: 11549.1 | BD42: 2561.66 | BE42: 2751.29 | BF42: =SUM(AX42:BE42) -> 40664.01 | BG42: =SUM(AL42:AW42) -> 55106.98 | BH42: 68187.63 | BI42: =SUM(N42:Y42) -> 46889.22 | BJ42: =SUM(BA42:BE42) -> 25565.72 | BK42: =SUM(AO42:AZ42) -> 56925.08 | BL42: =SUM(AC42:AN42) -> 70413.39 | BM42: =SUM(Q42:AB42) -> 49161.65 | BN42: =SUM(E42:P42) -> 39812.65 | BO42: =SUM(B42:D42) -> 27
A43: 4093 - Recruitment expenses | N43: 16125 | W43: 1035 | X43: 1099.5 | Y43: 3090 | Z43: 344.85 | AA43: 16657.5 | AB43: 2160 | AC43: 14619 | AD43: 2490 | AE43: 0 | AF43: 0 | AG43: 0 | AH43: 0 | AI43: 0 | AJ43: 0 | AK43: 0 | AL43: 0 | AM43: 0 | AN43: 0 | AO43: 0 | AP43: 0 | AQ43: 0 | AR43: 0 | AS43: 0 | AT43: 0 | AU43: 0 | AV43: 0 | AW43: 0 | AX43: 0 | AY43: 0 | AZ43: 0 | BA43: 0 | BF43: =SUM(AX43:BE43) -> 0 | BG43: =SUM(AL43:AW43) -> 0 | BH43: 36271.35 | BI43: =SUM(N43:Y43) -> 21349.5 | BJ43: =SUM(BA43:BE43) -> 0 | BK43: =SUM(AO43:AZ43) -> 0 | BL43: =SUM(AC43:AN43) -> 17109 | BM43: =SUM(Q43:AB43) -> 24386.85 | BN43: =SUM(E43:P43) -> 16125 | BO43: =SUM(B43:D43) -> 0
A44: 4099 - Other personnel expenses | C44: 43.6 | D44: -12.7 | Z44: 1110 | AB44: 290.98 | AC44: 0 | AD44: 1500 | AE44: 0 | AF44: 1321.32 | AG44: 28 | AH44: 28 | AI44: 28 | AJ44: 28 | AK44: 28 | AL44: 238.21 | AM44: 217.86 | AN44: 238.21 | AO44: 231.42 | AP44: 238.21 | AQ44: 231.42 | AR44: 238.21 | AS44: 238.21 | AT44: 231.42 | AU44: 238.21 | AV44: 231.42 | AW44: 2735.49 | AX44: 332.76 | AY44: 303.99 | AZ44: 332.76 | BA44: 323.17 | BB44: 332.76 | BC44: 323.17 | BD44: 332.76 | BE44: 332.76 | BF44: =SUM(AX44:BE44) -> 2614.13 | BG44: =SUM(AL44:AW44) -> 5308.29 | BH44: 4362.3 | BI44: =SUM(N44:Y44) -> 0 | BJ44: =SUM(BA44:BE44) -> 1644.62 | BK44: =SUM(AO44:AZ44) -> 5583.52 | BL44: =SUM(AC44:AN44) -> 3655.6 | BM44: =SUM(Q44:AB44) -> 1400.98 | BN44: =SUM(E44:P44) -> 0 | BO44: =SUM(B44:D44) -> 30.9
A45: Total: Personnel Expenses | B45: =SUM(B26:B44) -> 71044.95 | C45: =SUM(C26:C44) -> 71784.63 | D45: =SUM(D26:D44) -> 72201.34 | E45: 70590.28 | F45: 73844.65 | G45: 121305.16 | H45: 77412.75 | I45: 79840.8 | J45: 85667.84 | K45: 90454.9 | L45: 100598.28 | M45: 95130.7 | N45: 111281.74 | O45: 96640.15 | P45: 113960.41 | Q45: =SUM(Q26:Q44) -> 93322.06 | R45: =SUM(R26:R44) -> 100348.13 | S45: =SUM(S26:S44) -> 191188.79 | T45: =SUM(T26:T44) -> 96817.61 | U45: =SUM(U26:U44) -> 82695.93 | V45: =SUM(V26:V44) -> 95162.36 | W45: =SUM(W26:W44) -> 97729.06 | X45: =SUM(X26:X44) -> 103532.57 | ... BE45: =SUM(BE26:BE44) -> 220384.75 | BF45: =SUM(AX45:BE45) -> 1655673.9 | BG45: =SUM(AL45:AW45) -> 2281330.1 | BH45: =SUM(Z45:AK45) -> 1761707.8 | BI45: =SUM(N45:Y45) -> 1298514.1 | BJ45: =SUM(BA45:BE45) -> 1082146.8 | BK45: =SUM(AO45:AZ45) -> 2375861.7 | BL45: =SUM(AC45:AN45) -> 1880665.3 | BM45: =SUM(Q45:AB45) -> 1336669.8 | BN45: =SUM(E45:P45) -> 1116727.7 | BO45: =SUM(B45:D45) -> 215030.92 | BP45: Personnel
A46: Housing Expenses
A47: 4100 - Rental expenses | B47: 4408.39 | C47: 4408.39 | D47: 4408.39 | E47: 4659.67 | F47: 4659.67 | G47: 4659.67 | H47: 4659.67 | I47: 4659.67 | J47: 4659.67 | K47: 4659.67 | L47: 4659.67 | M47: 4659.67 | N47: 4659.67 | O47: 4659.67 | P47: 4659.67 | Q47: 5000 | R47: 5000 | S47: 5000 | T47: 5000 | U47: 5000 | V47: 5000 | W47: 5000 | X47: 5000 | Y47: 5000 | Z47: 5000 | AA47: 5000 | AB47: 5000 | AC47: 0 | AD47: 0 | AE47: 0 | AF47: 10865.64 | AG47: 8635.33 | AH47: 7891.88 | AI47: 8635.32 | AJ47: 8635.32 | AK47: 8635.32 | AL47: 8635.32 | AM47: 8635.32 | AN47: 8635.32 | AO47: 8635.32 | AP47: 8635.32 | AQ47: 8635.32 | AR47: 8927.32 | AS47: 8927.32 | AT47: 8927.32 | AU47: 8927.32 | AV47: 8927.32 | AW47: 8927.32 | AX47: 8927.32 | AY47: 8927.32 | AZ47: 8927.32 | BA47: 9993.2 | BB47: 8268.88 | BC47: 9033.88 | BD47: 9238.48 | BE47: 9238.48 | BF47: =SUM(AX47:BE47) -> 72554.88 | BG47: =SUM(AL47:AW47) -> 105375.84 | BH47: =SUM(Z47:AK47) -> 68298.81 | BI47: =SUM(N47:Y47) -> 58979.01 | BJ47: =SUM(BA47:BE47) -> 45772.92 | BK47: =SUM(AO47:AZ47) -> 106251.84 | BL47: =SUM(AC47:AN47) -> 79204.77 | BM47: =SUM(Q47:AB47) -> 60000 | BN47: =SUM(E47:P47) -> 55916.04 | BO47: =SUM(B47:D47) -> 13225.17
A48: 4170 - Security expenses | D48: 0 | E48: 32.88 | F48: 33.97 | G48: 32.88 | H48: 33.97 | I48: 33.97 | J48: 32.88 | K48: 33.97 | L48: 32.88 | M48: 33.97 | N48: 33.97 | O48: 30.68 | P48: 33.98 | Q48: 480 | AC48: 0 | AD48: 0 | AE48: 0 | AF48: 0 | AG48: 0 | AH48: 0 | AI48: 0 | AJ48: 0 | AK48: 0 | AL48: 0 | AM48: 0 | AN48: 0 | AO48: 0 | AP48: 0 | AQ48: 0 | AR48: 0 | AS48: 0 | AT48: 0 | AU48: 0 | AV48: 0 | AW48: 0 | AX48: 0 | AY48: 0 | AZ48: 0 | BA48: 0 | BF48: =SUM(AX48:BE48) -> 0 | BG48: =SUM(AL48:AW48) -> 0 | BI48: =SUM(N48:Y48) -> 578.63 | BJ48: =SUM(BA48:BE48) -> 0 | BK48: =SUM(AO48:AZ48) -> 0 | BL48: =SUM(AC48:AN48) -> 0 | BM48: =SUM(Q48:AB48) -> 480 | BN48: =SUM(E48:P48) -> 400 | BO48: =SUM(B48:D48) -> 0
A49: 4180 - Utilities expenses | B49: 207.23 | C49: 184.3 | D49: 184.29 | E49: 25.33 | F49: 162.36 | G49: 185.05 | H49: 171.54 | I49: 142.98 | J49: 350.82 | L49: -14.05 | M49: -21.59 | N49: 203.89 | O49: 196.26 | P49: -155.92 | Q49: 392.52 | R49: 203.71 | S49: 28.44 | T49: 189.26 | U49: 189.26 | V49: 189.27 | W49: 253.29 | X49: 229 | Y49: 202.39 | Z49: 368.84 | AA49: 218.06 | AB49: 9.11 | AC49: 189.31 | AD49: 406.97 | AE49: 395.32 | AF49: 453.72 | AG49: 453.72 | AH49: 441.3 | AI49: 600.64 | AJ49: 440.88 | AK49: 440.88 | AL49: 469.05 | AM49: 469.05 | AN49: 469.05 | AO49: 469.05 | AP49: 756.71 | AQ49: 345.35 | AR49: 469.05 | AS49: 469.05 | AT49: 469.05 | AU49: 541.61 | AV49: 469.05 | AW49: 469.05 | AX49: 495.93 | AY49: 649.29 | AZ49: 495.93 | BA49: 495.93 | BB49: 495.93 | BC49: 495.93 | BD49: 495.93 | BE49: 495.93 | BF49: =SUM(AX49:BE49) -> 4120.8 | BG49: =SUM(AL49:AW49) -> 5865.12 | BH49: =SUM(Z49:AK49) -> 4418.75 | BI49: =SUM(N49:Y49) -> 2121.37 | BJ49: =SUM(BA49:BE49) -> 2479.65 | BK49: =SUM(AO49:AZ49) -> 6099.12 | BL49: =SUM(AC49:AN49) -> 5229.89 | BM49: =SUM(Q49:AB49) -> 2473.15 | BN49: =SUM(E49:P49) -> 1246.67 | BO49: =SUM(B49:D49) -> 575.82
A50: 4190 - Other housing costs | AC50: 1125.54 | AD50: 0 | AE50: 0 | AF50: 347.07 | AG50: 0 | AH50: 0 | AI50: 0 | AJ50: 0 | AK50: 0 | AL50: 0 | AM50: 0 | AN50: 0 | AO50: 0 | AP50: 0 | AQ50: 0 | AR50: 0 | AS50: 0 | AT50: 0 | AU50: 0 | AV50: 0 | AW50: 0 | AX50: 0 | AY50: 0 | AZ50: 0 | BA50: 0 | BF50: =SUM(AX50:BE50) -> 0 | BG50: =SUM(AL50:AW50) -> 0 | BH50: =SUM(Z50:AK50) -> 1472.61 | BI50: =SUM(N50:Y50) -> 0 | BJ50: =SUM(BA50:BE50) -> 0 | BK50: =SUM(AO50:AZ50) -> 0 | BL50: =SUM(AC50:AN50) -> 1472.61
A51: Total: Housing Expenses | B51: 4615.62 | C51: 4592.69 | D51: =SUM(D47:D49) -> 4592.68 | E51: 4717.88 | F51: 4856 | G51: 4877.6 | H51: 4865.18 | I51: 4836.62 | J51: 5043.37 | K51: 4693.64 | L51: 4678.5 | M51: 4672.05 | N51: 4897.53 | O51: 4886.61 | P51: 4537.73 | Q51: =SUM(Q47:Q49) -> 5872.52 | R51: =SUM(R47:R49) -> 5203.71 | S51: =SUM(S47:S49) -> 5028.44 | T51: =SUM(T47:T49) -> 5189.26 | U51: =SUM(U47:U49) -> 5189.26 | V51: =SUM(V47:V49) -> 5189.27 | W51: =SUM(W47:W49) -> 5253.29 | X51: =SUM(X47:X49) -> 5229 | ... AB51: =SUM(AB47:AB49) -> 5009.11 | AC51: =SUM(AC47:AC50) -> 1314.85 | AD51: =SUM(AD47:AD50) -> 406.97 | AE51: =SUM(AE47:AE50) -> 395.32 | AF51: =SUM(AF47:AF50) -> 11666.43 | AG51: =SUM(AG47:AG50) -> 9089.05 | AH51: =SUM(AH47:AH50) -> 8333.18 | AI51: =SUM(AI47:AI50) -> 9235.96 | AJ51: =SUM(AJ47:AJ50) -> 9076.2 | ... BE51: =SUM(BE47:BE50) -> 9734.41 | BF51: =SUM(AX51:BE51) -> 76675.68 | BG51: =SUM(AL51:AW51) -> 111240.96 | BH51: =SUM(Z51:AK51) -> 74190.17 | BI51: =SUM(N51:Y51) -> 61679.01 | BJ51: =SUM(BA51:BE51) -> 48252.57 | BK51: =SUM(AO51:AZ51) -> 112350.96 | BL51: =SUM(AC51:AN51) -> 85907.27 | BM51: =SUM(Q51:AB51) -> 62953.15 | BN51: =SUM(E51:P51) -> 57562.71 | BO51: =SUM(B51:D51) -> 13800.99 | BP51: General
A52: Maintenance and small equipment | AO52: 0 | AP52: 0 | AQ52: 0 | AR52: 0 | AS52: 0 | AT52: 0 | AU52: 0 | AV52: 0 | AW52: 0 | AX52: 0 | AY52: 0 | AZ52: 0
A53: 4200 - Maintenance and small equipment | B53: 109.5 | C53: 49.84 | D53: 0 | AC53: 0 | AD53: 0 | AE53: 0 | AF53: 0 | AG53: 0 | AH53: 0 | AI53: 0 | AJ53: 0 | AK53: 0 | AL53: 0 | AM53: 0 | AN53: 0 | AO53: 0 | AP53: 0 | AQ53: 0 | AR53: 0 | AS53: 0 | AT53: 0 | AU53: 0 | AV53: 0 | AW53: 0 | AX53: 0 | AY53: 0 | AZ53: 0 | BA53: 0 | BF53: =SUM(AX53:BE53) -> 0 | BG53: =SUM(AL53:AW53) -> 0 | BI53: =SUM(N53:Y53) -> 0 | BJ53: =SUM(BA53:BE53) -> 0 | BK53: =SUM(AO53:AZ53) -> 0 | BL53: =SUM(AC53:AN53) -> 0 | BM53: =SUM(Q53:AB53) -> 0 | BN53: =SUM(E53:P53) -> 0 | BO53: =SUM(B53:D53) -> 159.34
A54: Total: Maintenance and small equipment | B54: 109.5 | C54: 49.84 | D54: =SUM(D53) -> 0 | AL54: =SUM(AL53) -> 0 | AM54: =SUM(AM53) -> 0 | AN54: =SUM(AN53) -> 0 | AO54: =SUM(AO53) -> 0 | AP54: =SUM(AP53) -> 0 | AQ54: =SUM(AQ53) -> 0 | AR54: =SUM(AR53) -> 0 | AS54: =SUM(AS53) -> 0 | ... AX54: =SUM(AX53) -> 0 | AY54: 0 | AZ54: 0 | BA54: 0 | BB54: 0 | BC54: 0 | BD54: 0 | BE54: 0 | BF54: =SUM(AX54:BE54) -> 0 | BG54: =SUM(AL54:AW54) -> 0 | BH54: =SUM(Z54:AK54) -> 0 | BI54: =SUM(N54:Y54) -> 0 | BJ54: =SUM(BA54:BE54) -> 0 | BK54: =SUM(AO54:AZ54) -> 0 | BL54: =SUM(AC54:AN54) -> 0 | BM54: =SUM(Q54:AB54) -> 0 | BN54: 0 | BO54: =SUM(B54:D54) -> 159.34 | BP54: General
A55: Office Expenses | AO55: 0 | AP55: 0 | AQ55: 0 | AR55: 0 | AS55: 0 | AT55: 0 | AU55: 0 | AV55: 0 | AW55: 0 | AX55: 0 | AY55: 0 | AZ55: 0 | BA55: 0 | BB55: 0 | BC55: 0 | BD55: 0 | BE55: 0 | BF55: =SUM(AX55:BE55) -> 0 | BJ55: =SUM(BA55:BE55) -> 0 | BK55: =SUM(AO55:AZ55) -> 0
A56: 4300 - Office expenses | L56: 2017.1 | M56: 2350.43 | Q56: 31.38 | T56: 2265.58 | U56: 90.42 | V56: 39.59 | W56: 458.64 | X56: 205.84 | Y56: 79.21 | Z56: 6022.08 | AB56: 1418.9 | AC56: 0 | AD56: 653.29 | AE56: 453 | AF56: 1540.4 | AG56: 0 | AH56: 79.25 | AI56: 119.41 | AJ56: 388.81 | AK56: 1812.02 | AL56: 3814.71 | AM56: 824.99 | AN56: 0 | AO56: 0 | AP56: 0 | AQ56: 214.32 | AR56: 0 | AS56: 114 | AT56: 2035.92 | AU56: 0 | AV56: 0 | AW56: 5552.76 | AX56: 108.75 | AY56: 57.23 | AZ56: 650 | BA56: 325 | BB56: 416.2 | BC56: 1871.11 | BD56: 3611.3 | BE56: 0 | BF56: =SUM(AX56:BE56) -> 7039.59 | BG56: =SUM(AL56:AW56) -> 12556.7 | BH56: =SUM(Z56:AK56) -> 12487.16 | BI56: =SUM(N56:Y56) -> 3170.66 | BJ56: =SUM(BA56:BE56) -> 6223.61 | BK56: =SUM(AO56:AZ56) -> 8732.98 | BL56: =SUM(AC56:AN56) -> 9685.88 | BM56: =SUM(Q56:AB56) -> 10611.64 | BN56: =SUM(E56:P56) -> 4367.53 | BO56: =SUM(B56:D56) -> 0
A57: 4302 - Postage and courier expenses | C57: 77.51 | D57: 0 | G57: 81.52 | H57: 220.09 | I57: -110.06 | J57: 84.44 | O57: 254.66 | W57: 65.49 | X57: 314.1 | Z57: 225.15 | AC57: 0 | AD57: 0 | AE57: 0 | AF57: 0 | AG57: 98.86 | AH57: 37.99 | AI57: 0 | AJ57: 0 | AK57: 0 | AL57: 405.29 | AM57: 0 | AN57: 106.46 | AO57: 0 | AP57: 0 | AQ57: 96.6 | AR57: 57 | AS57: 0 | AT57: 71.86 | AU57: 0 | AV57: 0 | AW57: 0 | AX57: 33.75 | AY57: 124.28 | AZ57: 176 | BA57: 0 | BF57: =SUM(AX57:BE57) -> 334.03 | BG57: =SUM(AL57:AW57) -> 737.21 | BH57: =SUM(Z57:AK57) -> 362 | BI57: =SUM(N57:Y57) -> 634.25 | BJ57: =SUM(BA57:BE57) -> 0 | BK57: =SUM(AO57:AZ57) -> 559.49 | BL57: =SUM(AC57:AN57) -> 648.6 | BM57: =SUM(Q57:AB57) -> 604.74 | BN57: =SUM(E57:P57) -> 530.65 | BO57: =SUM(B57:D57) -> 77.51
A58: 4305 - Subscriptions and contributions | C58: 112.52 | D58: 0 | G58: 2353.41 | H58: 6760 | I58: 2453.44 | J58: 1760 | K58: 1760 | M58: 3633 | N58: 2047.1 | O58: 1964.17 | P58: 1855.44 | Q58: 2277.36 | R58: 2007.9 | S58: 3788.92 | T58: 2411.16 | U58: 2411.16 | V58: 2465.9 | W58: 2434.93 | X58: 2356.38 | Y58: 530.12 | Z58: 3469.46 | AA58: 5290.67 | AB58: 1796.31 | AC58: 8244.14 | AD58: 1281.65 | AE58: 7149.43 | AF58: 31.45 | AG58: 316.08 | AH58: 7561.56 | AI58: 1788.05 | AJ58: 2536.24 | AK58: 7354.48 | AL58: 1673.53 | AM58: 768.83 | AN58: 9495.94 | AO58: 537.85 | AP58: 3660.8 | AQ58: 9373.39 | AR58: 2942.42 | AS58: 3247.69 | AT58: 5482.55 | AU58: 3546.24 | AV58: 5080.71 | AW58: 3334.99 | AX58: 3561.26 | AY58: 7564.72 | AZ58: 6498.85 | BA58: 5960.13 | BB58: 5134.04 | BC58: 4111.62 | BD58: 5703.73 | BE58: 7567.95 | BF58: =SUM(AX58:BE58) -> 46102.3 | BG58: =SUM(AL58:AW58) -> 49144.94 | BH58: =SUM(Z58:AK58) -> 46819.52 | BI58: =SUM(N58:Y58) -> 26550.54 | BJ58: =SUM(BA58:BE58) -> 28477.47 | BK58: =SUM(AO58:AZ58) -> 54831.47 | BL58: =SUM(AC58:AN58) -> 48201.38 | BM58: =SUM(Q58:AB58) -> 31240.27 | BN58: =SUM(E58:P58) -> 24586.56 | BO58: =SUM(B58:D58) -> 112.52
A59: 4330 - Telephone expenses | B59: 87.62 | D59: -436.36 | F59: 54.62 | G59: 51.74 | I59: 50.83 | L59: 135.71 | M59: 52.07 | N59: 80.97 | P59: 119.05 | Q59: -43.8 | R59: 86.36 | S59: 86.34 | T59: 125.47 | U59: 48.94 | V59: 117.08 | W59: 69 | X59: 69.15 | Y59: 129.6 | Z59: 69.43 | AA59: 132.03 | AB59: 1879.04 | AC59: 0 | AD59: 71.62 | AE59: 81.6 | AF59: 78.12 | AG59: 147.1 | AH59: 78.38 | AI59: 7.4 | AJ59: 74.48 | AK59: 77.11 | AL59: 93.11 | AM59: 5.91 | AN59: 71 | AO59: 77.74 | AP59: 80.44 | AQ59: 75.58 | AR59: 78.57 | AS59: 78.86 | AT59: 78.92 | AU59: 79.69 | AV59: 80.52 | AW59: 81.93 | AX59: 79.36 | AY59: 76.02 | AZ59: 77.13 | BA59: 77.52 | BB59: 53.5 | BC59: 138.71 | BD59: 0 | BE59: 66.11 | BF59: =SUM(AX59:BE59) -> 568.35 | BG59: =SUM(AL59:AW59) -> 882.27 | BH59: =SUM(Z59:AK59) -> 2696.31 | BI59: =SUM(N59:Y59) -> 888.16 | BJ59: =SUM(BA59:BE59) -> 335.84 | BK59: =SUM(AO59:AZ59) -> 944.76 | BL59: =SUM(AC59:AN59) -> 785.83 | BM59: =SUM(Q59:AB59) -> 2768.64 | BN59: =SUM(E59:P59) -> 544.99 | BO59: =SUM(B59:D59) -> -348.74
A60: Total: Office Expenses | B60: 87.62 | C60: 190.03 | D60: =SUM(D56:D59) -> -436.36 | F60: 54.62 | G60: 2486.67 | H60: 6980.09 | I60: 2394.21 | J60: 1844.44 | K60: 1760 | L60: 2152.81 | M60: 6035.5 | N60: 2128.07 | O60: 2218.83 | P60: 1974.49 | Q60: =SUM(Q56:Q59) -> 2264.94 | R60: =SUM(R56:R59) -> 2094.26 | S60: =SUM(S56:S59) -> 3875.26 | T60: =SUM(T56:T59) -> 4802.21 | U60: =SUM(U56:U59) -> 2550.52 | V60: =SUM(V56:V59) -> 2622.57 | W60: =SUM(W56:W59) -> 3028.06 | X60: =SUM(X56:X59) -> 2945.47 | ... BE60: =SUM(BE56:BE59) -> 7634.06 | BF60: =SUM(AX60:BE60) -> 54044.27 | BG60: =SUM(AL60:AW60) -> 63321.12 | BH60: =SUM(Z60:AK60) -> 62364.99 | BI60: =SUM(N60:Y60) -> 31243.61 | BJ60: =SUM(BA60:BE60) -> 35036.92 | BK60: =SUM(AO60:AZ60) -> 65068.7 | BL60: =SUM(AC60:AN60) -> 59321.69 | BM60: =SUM(Q60:AB60) -> 45225.29 | BN60: =SUM(E60:P60) -> 30029.73 | BO60: =SUM(B60:D60) -> -158.71 | BP60: General
A61: Car Expenses
A62: 4491 - Parking costs | D62: 0 | E62: 459.34 | I62: 459.34 | Q62: 75.3 | R62: 77.81 | S62: 75.3 | T62: 77.81 | U62: 77.81 | V62: 75.31 | W62: 81.31 | X62: 78.69 | Y62: 81.31 | Z62: 81.31 | AA62: 76.07 | AB62: 586.29 | AC62: 0 | AD62: 0 | AE62: 0 | AF62: 0 | AG62: 0 | AH62: 0 | AI62: 0 | AJ62: 0 | AK62: 0 | AL62: 0 | AM62: 0 | AN62: 0 | AO62: 0 | AP62: 0 | AQ62: 0 | AR62: 0 | AS62: 0 | AT62: 0 | AU62: 0 | AV62: 0 | AW62: 0 | AX62: 0 | AY62: 0 | AZ62: 0 | BA62: 0 | BF62: =SUM(AX62:BE62) -> 0 | BG62: =SUM(AL62:AW62) -> 0 | BI62: =SUM(N62:Y62) -> 700.65 | BJ62: =SUM(BA62:BE62) -> 0 | BK62: =SUM(AO62:AZ62) -> 0 | BL62: =SUM(AC62:AN62) -> 0 | BM62: =SUM(Q62:AB62) -> 1444.32 | BN62: =SUM(E62:P62) -> 918.68 | BO62: =SUM(B62:D62) -> 0
A63: Total: Car Expenses | D63: 0 | E63: 459.34 | I63: 459.34 | Q63: =SUM(Q62) -> 75.3 | R63: =SUM(R62) -> 77.81 | S63: =SUM(S62) -> 75.3 | T63: =SUM(T62) -> 77.81 | U63: 77.81 | V63: 75.31 | W63: =SUM(W62) -> 81.31 | X63: =SUM(X62) -> 78.69 | Y63: =SUM(Y62) -> 81.31 | Z63: =SUM(Z62) -> 81.31 | AA63: =SUM(AA62) -> 76.07 | AB63: =SUM(AB62) -> 586.29 | AC63: =SUM(AC62) -> 0 | AD63: =SUM(AD62) -> 0 | ... BE63: =SUM(BE62) -> 0 | BF63: =SUM(AX63:BE63) -> 0 | BG63: =SUM(AL63:AW63) -> 0 | BH63: =SUM(Z63:AK63) -> 743.67 | BI63: =SUM(N63:Y63) -> 700.65 | BJ63: =SUM(BA63:BE63) -> 0 | BK63: =SUM(AO63:AZ63) -> 0 | BL63: =SUM(AC63:AN63) -> 0 | BM63: =SUM(Q63:AB63) -> 1444.32 | BN63: =SUM(E63:P63) -> 918.68 | BO63: =SUM(B63:D63) -> 0 | BP63: General
A64: Sales Expenses | AY64: 0 | AZ64: 0 | BA64: 0 | BB64: 0 | BC64: 0 | BD64: 0 | BE64: 0 | BF64: =SUM(AX64:BE64) -> 0 | BJ64: =SUM(BA64:BE64) -> 0 | BK64: =SUM(AO64:AZ64) -> 0
A65: 4500 - Promotion expenses | C65: 5000 | H65: 9600 | I65: 8925 | J65: 1813 | K65: 5155 | L65: 16221 | M65: 4850 | N65: 6674 | O65: -1183.24 | P65: 1235.07 | Q65: 2518 | R65: 9498 | S65: 7901.07 | T65: 3320 | U65: 4150 | V65: 2765.07 | W65: 1950 | X65: 4960 | Y65: 8852.5 | Z65: 2768.47 | AA65: 4446.78 | AB65: 2966.58 | AC65: 5640 | AD65: 3099.96 | AE65: 1755 | AF65: 8282.9 | AG65: 2971.32 | AH65: 2953.25 | AI65: 3395.31 | AJ65: 10372.85 | AK65: 6817.75 | AL65: 7032.5 | AM65: 1217.5 | AN65: 2234.04 | AO65: 675 | AP65: 13179.5 | AQ65: 19187.04 | AR65: 0 | AS65: 0 | AT65: 2290.04 | AU65: 771.61 | AV65: 1208.5 | AW65: 1521.61 | AX65: 96.61 | AY65: 87.26 | AZ65: 19747.21 | BA65: -2782.92 | BB65: 16950.08 | BC65: 1053.23 | BD65: 2534.03 | BE65: 3623.75 | BF65: =SUM(AX65:BE65) -> 41309.25 | BG65: =SUM(AL65:AW65) -> 49317.34 | BH65: =SUM(Z65:AK65) -> 55470.17 | BI65: =SUM(N65:Y65) -> 52640.47 | BJ65: =SUM(BA65:BE65) -> 21378.17 | BK65: =SUM(AO65:AZ65) -> 58764.38 | BL65: =SUM(AC65:AN65) -> 55772.38 | BM65: =SUM(Q65:AB65) -> 56096.47 | BN65: =SUM(E65:P65) -> 53289.83 | BO65: =SUM(B65:D65) -> 5000
A66: 4501 - Sponsoring | B66: 225 | C66: 225 | D66: 225 | E66: 225 | F66: 225 | G66: 225 | H66: 225 | I66: 225 | J66: 225 | K66: 225 | L66: 225 | M66: 225 | N66: 275.56 | O66: 248.89 | P66: 275.55 | Q66: 1320 | V66: 800 | W66: 800 | AC66: 800 | AD66: 0 | AE66: 2500 | AF66: 0 | AG66: 0 | AH66: 7169.74 | AI66: 0 | AJ66: 0 | AK66: 0 | AL66: 0 | AM66: 0 | AN66: 0 | AO66: 0 | AP66: 0 | AQ66: 0 | AR66: 0 | AS66: 0 | AT66: 0 | AU66: 0 | AV66: 0 | AW66: 0 | AX66: 0 | AY66: 0 | AZ66: 0 | BA66: 0 | BF66: =SUM(AX66:BE66) -> 0 | BG66: =SUM(AL66:AW66) -> 0 | BH66: =SUM(Z66:AK66) -> 10469.74 | BI66: =SUM(N66:Y66) -> 3720 | BJ66: =SUM(BA66:BE66) -> 0 | BK66: =SUM(AO66:AZ66) -> 0 | BL66: =SUM(AC66:AN66) -> 10469.74 | BM66: =SUM(Q66:AB66) -> 2920 | BN66: =SUM(E66:P66) -> 2825 | BO66: =SUM(B66:D66) -> 675
A67: 4505 - Advertisement & Marketing Expenses | AC67: 0 | AD67: 0 | AE67: 0 | AF67: 0 | AG67: 0 | AH67: 0 | AI67: 0 | AJ67: 6000 | AK67: 0 | AL67: 655.58 | AM67: 451.76 | AN67: 606.12 | AO67: 687.47 | AP67: 462.82 | AQ67: 511.88 | AR67: 0 | AS67: 5661.13 | AT67: 7995.05 | AU67: 2595.04 | AV67: 2511.33 | AW67: 5395.04 | AX67: 2595.04 | AY67: 2343.91 | AZ67: 2595.03 | BA67: 2400 | BB67: 0 | BC67: 7119.31 | BD67: 5550.82 | BE67: 2800 | BF67: =SUM(AX67:BE67) -> 25404.11 | BG67: =SUM(AL67:AW67) -> 27533.22 | BH67: =SUM(Z67:AK67) -> 6000 | BI67: =SUM(N67:Y67) -> 0 | BJ67: =SUM(BA67:BE67) -> 17870.13 | BK67: =SUM(AO67:AZ67) -> 33353.74 | BL67: =SUM(AC67:AN67) -> 7713.46 | BM67: =SUM(Q67:AB67) -> 0 | BN67: =SUM(E67:P67) -> 0 | BO67: =SUM(B67:D67) -> 0
A68: 4510 - Business gifts | M68: 71.7 | Q68: 38.55 | AC68: 0 | AD68: 0 | AE68: 0 | AF68: 0 | AG68: 0 | AH68: 0 | AI68: 0 | AJ68: 0 | AK68: 0 | AL68: 0 | AM68: 0 | AN68: 0 | AO68: 0 | AP68: 0 | AQ68: 0 | AR68: 0 | AS68: 0 | AT68: 0 | AU68: 0 | AV68: 0 | AW68: 0 | AX68: 0 | AY68: 0 | AZ68: 0 | BA68: 0 | BF68: =SUM(AX68:BE68) -> 0 | BG68: =SUM(AL68:AW68) -> 0 | BI68: =SUM(N68:Y68) -> 38.55 | BJ68: =SUM(BA68:BE68) -> 0 | BK68: =SUM(AO68:AZ68) -> 0 | BL68: =SUM(AC68:AN68) -> 0 | BM68: =SUM(Q68:AB68) -> 38.55 | BN68: =SUM(E68:P68) -> 71.7 | BO68: =SUM(B68:D68) -> 0
A69: 4515 - Entertainment and representation expenses | M69: 227.75 | P69: 230 | Z69: 1751.07 | AC69: 0 | AD69: 796.58 | AE69: 0 | AF69: 0 | AG69: 0 | AH69: 0 | AI69: 247.45 | AJ69: 0 | AK69: 0 | AL69: 0 | AM69: 0 | AN69: 0 | AO69: 0 | AP69: 0 | AQ69: 0 | AR69: 0 | AS69: 0 | AT69: 0 | AU69: 0 | AV69: 0 | AW69: 0 | AX69: 0 | AY69: 0 | AZ69: 0 | BA69: 0 | BF69: =SUM(AX69:BE69) -> 0 | BG69: =SUM(AL69:AW69) -> 0 | BH69: =SUM(Z69:AK69) -> 2795.1 | BI69: =SUM(N69:Y69) -> 230 | BJ69: =SUM(BA69:BE69) -> 0 | BK69: =SUM(AO69:AZ69) -> 0 | BL69: =SUM(AC69:AN69) -> 1044.03 | BM69: =SUM(Q69:AB69) -> 1751.07 | BN69: =SUM(E69:P69) -> 457.75 | BO69: =SUM(B69:D69) -> 0
A70: 4530 - Travel costs | W70: 582.05 | X70: 6760.58 | Y70: 1344 | Z70: 210.07 | AA70: 4866.04 | AB70: 12352.37 | AC70: 0 | AD70: 10219.92 | AE70: 3288.88 | AF70: 2262.09 | AG70: 1742.63 | AH70: 745.02 | AI70: 3054.39 | AJ70: 4980.23 | AK70: 3521.4 | AL70: 3016.85 | AM70: 438.97 | AN70: 604.26 | AO70: 2798.04 | AP70: 8032.21 | AQ70: 520.16 | AR70: 4058.16 | AS70: 0 | AT70: 882.87 | AU70: 384.6 | AV70: 2281.87 | AW70: 9534.2 | AX70: 0 | AY70: 761.49 | AZ70: 257.77 | BA70: 0 | BB70: 0 | BC70: 3242.74 | BD70: 0 | BE70: 0 | BF70: =SUM(AX70:BE70) -> 4262 | BG70: =SUM(AL70:AW70) -> 32552.19 | BH70: =SUM(Z70:AK70) -> 47243.04 | BI70: =SUM(N70:Y70) -> 8686.63 | BJ70: =SUM(BA70:BE70) -> 3242.74 | BK70: =SUM(AO70:AZ70) -> 29511.37 | BL70: =SUM(AC70:AN70) -> 33874.64 | BM70: =SUM(Q70:AB70) -> 26115.11 | BN70: =SUM(E70:P70) -> 0 | BO70: =SUM(B70:D70) -> 0
A71: 4560 - Write off bad debts | P71: 38038.75 | U71: 6500 | V71: 3250 | AC71: 0 | AD71: 0 | AE71: 0 | AF71: 0 | AG71: 0 | AH71: 0 | AI71: 0 | AJ71: 0 | AK71: 0 | AL71: 0 | AM71: 0 | AN71: 0 | AO71: 0 | AP71: 0 | AQ71: 0 | AR71: 0 | AS71: 0 | AT71: 0 | AU71: 0 | AV71: 0 | AW71: 0 | AX71: 0 | AY71: 0 | AZ71: 0 | BA71: 0 | BB71: 0 | BC71: 0 | BD71: 0 | BE71: 3150 | BF71: =SUM(AX71:BE71) -> 3150 | BG71: =SUM(AL71:AW71) -> 0 | BI71: =SUM(N71:Y71) -> 47788.75 | BJ71: =SUM(BA71:BE71) -> 3150 | BK71: =SUM(AO71:AZ71) -> 0 | BL71: =SUM(AC71:AN71) -> 0 | BM71: =SUM(Q71:AB71) -> 9750 | BN71: =SUM(E71:P71) -> 38038.75 | BO71: =SUM(B71:D71) -> 0
A72: 4550 - Conference fees | D72: 0 | G72: 1856.23 | L72: 5140.54 | M72: 2082.58 | N72: 651.15 | T72: 12929.26 | V72: 13832.53 | AB72: 7529.82 | AC72: 0 | AD72: -2141.26 | AE72: 7500 | AF72: 4592.21 | AG72: 770 | AH72: 0 | AI72: 0 | AJ72: 7802.33 | AK72: 2428.59 | AL72: 2153.25 | AM72: 1228.09 | AN72: 452.87 | AO72: 5409.08 | AP72: 360 | AQ72: 108.54 | AR72: 0 | AS72: 0 | AT72: 7851.63 | AU72: 0 | AV72: 195.24 | AW72: 5406.19 | AX72: 4944 | AY72: 0 | AZ72: 1044.37 | BA72: 0 | BB72: 451.38 | BC72: 736.42 | BD72: 103.76 | BE72: 785.37 | BF72: =SUM(AX72:BE72) -> 8065.3 | BG72: =SUM(AL72:AW72) -> 23164.89 | BH72: =SUM(Z72:AK72) -> 28481.69 | BI72: =SUM(N72:Y72) -> 27412.94 | BJ72: =SUM(BA72:BE72) -> 2076.93 | BK72: =SUM(AO72:AZ72) -> 25319.05 | BL72: =SUM(AC72:AN72) -> 24786.08 | BM72: =SUM(Q72:AB72) -> 34291.61 | BN72: =SUM(E72:P72) -> 9730.5 | BO72: =SUM(B72:D72) -> 0
A73: 4590 - Other sales costs | M73: 2340 | R73: 7200 | U73: 21434.15 | V73: 7000 | W73: 9238.82 | X73: 3500 | Y73: 21046.2 | AA73: 7000 | AB73: 13000 | AC73: 3000 | AD73: 4000 | AE73: 0 | AF73: 5000 | AG73: 10772.06 | AH73: 12082.64 | AI73: 7772.06 | AJ73: 10482.64 | AK73: 11497.06 | AL73: 16058.57 | AM73: 10528.79 | AN73: 18272.06 | AO73: 14139.11 | AP73: 14960.41 | AQ73: 13939.11 | AR73: 12960.37 | AS73: 11251.12 | AT73: 8533.24 | AU73: 6140.57 | AV73: 10192.49 | AW73: 12236.85 | AX73: 30670.83 | AY73: 2897.38 | AZ73: 6501.96 | BA73: 6141.99 | BB73: 6346.71 | BC73: 6141.99 | BD73: 6346.72 | BE73: 4091.37 | BF73: =SUM(AX73:BE73) -> 69138.95 | BG73: =SUM(AL73:AW73) -> 149212.69 | BH73: =SUM(Z73:AK73) -> 84606.46 | BI73: =SUM(N73:Y73) -> 69419.17 | BJ73: =SUM(BA73:BE73) -> 29068.78 | BK73: =SUM(AO73:AZ73) -> 144423.44 | BL73: =SUM(AC73:AN73) -> 109465.88 | BM73: =SUM(Q73:AB73) -> 89419.17 | BN73: =SUM(E73:P73) -> 2340 | BO73: =SUM(B73:D73) -> 0
A74: Total: Sales Expenses | B74: 225 | C74: 5225 | D74: =SUM(D65:D73) -> 225 | E74: 225 | F74: 225 | G74: 2081.23 | H74: 9825 | I74: 9150 | J74: 2038 | K74: 5380 | L74: 21586.54 | M74: 9797.03 | N74: 7600.71 | O74: -934.35 | P74: 39779.37 | Q74: =SUM(Q65:Q73) -> 3876.55 | R74: =SUM(R65:R73) -> 16698 | S74: =SUM(S65:S73) -> 7901.07 | T74: =SUM(T65:T73) -> 16249.26 | U74: =SUM(U65:U73) -> 32084.15 | V74: =SUM(V65:V73) -> 27647.6 | W74: =SUM(W65:W73) -> 12570.87 | X74: =SUM(X65:X73) -> 15220.58 | ... BE74: =SUM(BE65:BE73) -> 14450.49 | BF74: =SUM(AX74:BE74) -> 151329.61 | BG74: =SUM(AL74:AW74) -> 281780.33 | BH74: =SUM(Z74:AK74) -> 235066.2 | BI74: =SUM(N74:Y74) -> 209936.51 | BJ74: =SUM(BA74:BE74) -> 76786.75 | BK74: =SUM(AO74:AZ74) -> 291371.98 | BL74: =SUM(AC74:AN74) -> 243126.21 | BM74: =SUM(Q74:AB74) -> 220381.98 | BN74: =SUM(E74:P74) -> 106753.53 | BO74: =SUM(B74:D74) -> 5675 | BP74: General
A75: General Expenses
A76: 4160 - Fees & Taxes | AO76: 0 | AP76: 0 | AQ76: 0 | AR76: 0 | AS76: 0 | AT76: 0 | AU76: 0 | AV76: 0 | AW76: 0 | AX76: 2782.24 | AY76: 0 | AZ76: 0 | BA76: 3274.8 | BB76: 114.97 | BC76: 0 | BD76: 0 | BE76: 0 | BF76: =SUM(AX76:BE76) -> 6172.01 | BG76: =SUM(AL76:AW76) -> 0 | BH76: =SUM(Z76:AK76) -> 0 | BI76: =SUM(N76:Y76) -> 0 | BJ76: =SUM(BA76:BE76) -> 3389.77 | BK76: =SUM(AO76:AZ76) -> 2782.24 | BL76: =SUM(AC76:AN76) -> 0
A77: 4700 - Administrative expenses | B77: 3651.5 | D77: 3061.75 | E77: 1250 | F77: 4844.5 | G77: 5033.12 | H77: 6500 | I77: 1250 | J77: 1250 | K77: 1250 | L77: 2012.5 | M77: -254.2 | N77: 3869 | O77: -5766.5 | P77: 2239.5 | Q77: 842.5 | R77: 573.5 | S77: 1235 | T77: 1608.75 | U77: 1493 | V77: 1973 | W77: 2459 | Y77: 5819.5 | Z77: 2954 | AA77: 3578.02 | AB77: 7753.02 | AC77: 5171.78 | AD77: 1938.01 | AE77: 0 | AF77: 7393.5 | AG77: 0 | AH77: 0 | AI77: 13144.45 | AJ77: 1863.25 | AK77: 310.25 | AL77: 258 | AM77: -861.99 | AN77: 918.51 | AO77: 473.01 | AP77: 0 | AQ77: 0 | AR77: 630 | AS77: 675 | AT77: 720 | AU77: 810 | AV77: 652.5 | AW77: 765 | AX77: 630 | AY77: 843.98 | AZ77: 686.02 | BA77: 742.5 | BB77: 0 | BC77: 0 | BD77: 0 | BE77: 174.24 | BF77: =SUM(AX77:BE77) -> 3076.74 | BG77: =SUM(AL77:AW77) -> 5040.03 | BH77: =SUM(Z77:AK77) -> 44106.28 | BI77: =SUM(N77:Y77) -> 16346.25 | BJ77: =SUM(BA77:BE77) -> 916.74 | BK77: =SUM(AO77:AZ77) -> 6885.51 | BL77: =SUM(AC77:AN77) -> 30135.76 | BM77: =SUM(Q77:AB77) -> 30289.29 | BN77: =SUM(E77:P77) -> 23477.92 | BO77: =SUM(B77:D77) -> 6713.25
A78: 4720 - Consulting fees | D78: 286.5 | E78: 1875 | F78: 283.75 | G78: 1242.5 | H78: 375 | I78: 1756.25 | J78: 1937.5 | K78: 2066.25 | L78: 6311.25 | M78: 19045 | N78: 8041.5 | O78: 1500.01 | P78: 5199.99 | Q78: 1670 | R78: 3920 | S78: 3313.33 | T78: 12566.66 | U78: 8500 | V78: 3712.06 | W78: 4588.33 | X78: 5113.08 | Y78: 8257.12 | Z78: 10020 | AA78: 23338.76 | AB78: 18373.25 | AC78: 22713.5 | AD78: 29713.75 | AE78: 36046.65 | AF78: 29196.64 | AG78: 33156.18 | AH78: 28011.09 | AI78: 31737.88 | AJ78: 41375.2 | AK78: 43448.88 | AL78: 59932.81 | AM78: 39958.75 | AN78: 33308.82 | AO78: 21377.27 | AP78: 31720.06 | AQ78: 42808.17 | AR78: 32855.73 | AS78: 18586.04 | AT78: 47700.56 | AU78: 42646.08 | AV78: 41582.56 | AW78: 30620.95 | AX78: 31374.81 | AY78: 58391.16 | AZ78: 44087.98 | BA78: 51493.52 | BB78: 45353.6 | BC78: 70965.76 | BD78: 62076.36 | BE78: 52322.69 | BF78: =SUM(AX78:BE78) -> 416065.88 | BG78: =SUM(AL78:AW78) -> 443097.8 | BH78: =SUM(Z78:AK78) -> 347131.78 | BI78: =SUM(N78:Y78) -> 66382.08 | BJ78: =SUM(BA78:BE78) -> 282211.93 | BK78: =SUM(AO78:AZ78) -> 443751.37 | BL78: =SUM(AC78:AN78) -> 428600.15 | BM78: =SUM(Q78:AB78) -> 103372.59 | BN78: =SUM(E78:P78) -> 49634 | BO78: =SUM(B78:D78) -> 286.5
A79: 4780 - Automation expenses | B79: 2938.41 | C79: 2942.25 | D79: 2867.46 | E79: 3241.55 | F79: 3415.28 | G79: 1607.1 | H79: 8340.84 | I79: 4740.36 | J79: 4684.45 | K79: 6941.9 | L79: 5205.62 | M79: 5006.56 | N79: 5562.04 | O79: 5538.49 | P79: 5878.75 | Q79: 12441.63 | R79: 7466.46 | S79: 5253.39 | T79: 5863.62 | U79: 6485.35 | V79: 7404.12 | W79: 5855.92 | X79: 6000.55 | Y79: 10385.25 | Z79: 7853.2 | AA79: 15733.25 | AB79: 40915.04 | AC79: 14621.29 | AD79: 9801.2 | AE79: 7747.33 | AF79: 27472.57 | AG79: 11969.06 | AH79: 10657.61 | AI79: 21272.72 | AJ79: 13801.58 | AK79: 11118.67 | AL79: 11198.71 | AM79: 11494.83 | AN79: 14369.28 | AO79: 12891.14 | AP79: 8254.33 | AQ79: 12004.59 | AR79: 11750.04 | AS79: 9130.46 | AT79: 18779.61 | AU79: 11090.43 | AV79: 16499.4 | AW79: 12211.73 | AX79: 15125.24 | AY79: 12365.88 | AZ79: 17553.54 | BA79: 25112.73 | BB79: 10572.87 | BC79: 10421.89 | BD79: 27954.19 | BE79: 18879.33 | BF79: =SUM(AX79:BE79) -> 137985.67 | BG79: =SUM(AL79:AW79) -> 149674.55 | BH79: =SUM(Z79:AK79) -> 192963.52 | BI79: =SUM(N79:Y79) -> 84135.57 | BJ79: =SUM(BA79:BE79) -> 92941.01 | BK79: =SUM(AO79:AZ79) -> 157656.39 | BL79: =SUM(AC79:AN79) -> 165524.85 | BM79: =SUM(Q79:AB79) -> 131657.78 | BN79: =SUM(E79:P79) -> 60162.94 | BO79: =SUM(B79:D79) -> 8748.12
A80: 4790 - Other general expenses | J80: 39.95 | K80: 13.99 | P80: -27.6 | AC80: 0 | AD80: 0 | AE80: 0 | AF80: 0 | AG80: 0 | AH80: 0 | AI80: 0 | AJ80: 0 | AK80: 5463.94 | AL80: 1385 | AM80: 0 | AN80: 68 | AO80: 0 | AP80: 0 | AQ80: 2385 | AR80: 0 | AS80: 946.5 | AT80: 0 | AU80: 2595.26 | AV80: 246.34 | AW80: 4290.03 | AX80: 0 | AY80: 810.03 | AZ80: 79.41 | BA80: 28.4 | BB80: 1179.84 | BC80: 235 | BD80: 109.09 | BE80: 186.17 | BF80: =SUM(AX80:BE80) -> 2627.94 | BG80: =SUM(AL80:AW80) -> 11916.13 | BH80: =SUM(Z80:AK80) -> 5463.94 | BI80: =SUM(N80:Y80) -> -27.6 | BJ80: =SUM(BA80:BE80) -> 1738.5 | BK80: =SUM(AO80:AZ80) -> 11352.57 | BL80: =SUM(AC80:AN80) -> 6916.94 | BM80: =SUM(Q80:AB80) -> 0 | BN80: =SUM(E80:P80) -> 26.34 | BO80: =SUM(B80:D80) -> 0
A81: Total: General Expenses | B81: 6589.91 | C81: 2942.25 | D81: =SUM(D77:D80) -> 6215.71 | E81: 6366.55 | F81: 8543.53 | G81: 7882.72 | H81: 15215.84 | I81: 7746.61 | J81: 7911.9 | K81: 10272.14 | L81: 13529.37 | M81: 23797.36 | N81: 17472.54 | O81: 1272 | P81: 13290.64 | Q81: =SUM(Q77:Q80) -> 14954.13 | R81: =SUM(R77:R80) -> 11959.96 | S81: =SUM(S77:S80) -> 9801.72 | T81: =SUM(T77:T80) -> 20039.03 | U81: =SUM(U77:U80) -> 16478.35 | V81: =SUM(V77:V80) -> 13089.18 | W81: =SUM(W77:W80) -> 12903.25 | X81: =SUM(X77:X80) -> 11113.63 | ... AW81: =SUM(AW77:AW80) -> 47887.71 | AX81: =SUM(AX76:AX80) -> 49912.29 | AY81: =SUM(AY76:AY80) -> 72411.05 | AZ81: =SUM(AZ76:AZ80) -> 62406.95 | BA81: =SUM(BA76:BA80) -> 80651.95 | BB81: =SUM(BB76:BB80) -> 57221.28 | BC81: =SUM(BC76:BC80) -> 81622.65 | BD81: =SUM(BD76:BD80) -> 90139.64 | BE81: =SUM(BE76:BE80) -> 71562.43 | BF81: =SUM(AX81:BE81) -> 565928.24 | BG81: =SUM(AL81:AW81) -> 609728.51 | BH81: =SUM(Z81:AK81) -> 589665.52 | BI81: =SUM(N81:Y81) -> 166836.3 | BJ81: =SUM(BA81:BE81) -> 381197.95 | BK81: =SUM(AO81:AZ81) -> 622428.08 | BL81: =SUM(AC81:AN81) -> 631177.7 | BM81: =SUM(Q81:AB81) -> 265319.66 | BN81: =SUM(E81:P81) -> 133301.2 | BO81: =SUM(B81:D81) -> 15747.87 | BP81: General
A82: Depreciation
A83: 4801 - Depreciation software | J83: 20 | K83: 20 | L83: 20 | M83: 20 | N83: 20 | O83: 20 | P83: 20 | Q83: 20 | R83: 20 | S83: 767.66 | T83: 573.79 | U83: 610.51 | V83: 547.16 | W83: 747.16 | X83: 747.16 | Y83: 747.16 | Z83: 747.16 | AA83: 747.16 | AB83: 822.3 | AC83: 942.3 | AD83: 1031.27 | AE83: 1031.27 | AF83: 1031.27 | AG83: 1031.27 | AH83: 1031.27 | AI83: 1031.27 | AJ83: 1031.27 | AK83: 1031.27 | AL83: 1031.27 | AM83: 1031.27 | AN83: 1031.27 | AO83: 1031.27 | AP83: 1031.27 | AQ83: 1031.27 | AR83: 1031.27 | AS83: 1031.27 | AT83: 1031.27 | AU83: 1031.27 | AV83: 1031.27 | AW83: 1031.27 | AX83: 1031.27 | AY83: 1031.27 | AZ83: 1031.27 | BA83: 1031.27 | BB83: 1031.27 | BC83: 1031.27 | BD83: 1031.27 | BE83: 1031.27 | BF83: =SUM(AX83:BE83) -> 8250.16 | BG83: =SUM(AL83:AW83) -> 12375.24 | BH83: =SUM(Z83:AK83) -> 11509.08 | BI83: =SUM(N83:Y83) -> 4840.6 | BJ83: =SUM(BA83:BE83) -> 5156.35 | BK83: =SUM(AO83:AZ83) -> 12375.24 | BL83: =SUM(AC83:AN83) -> 12286.27 | BM83: =SUM(Q83:AB83) -> 7097.22 | BN83: =SUM(E83:P83) -> 140 | BO83: =SUM(B83:D83) -> 0
A84: 4802 - Depreciation computers | B84: 452.64 | C84: 452.64 | D84: 452.64 | E84: 452.64 | F84: 452.64 | G84: 452.64 | H84: 452.64 | I84: 452.64 | J84: 502.23 | K84: 213.6 | L84: 213.6 | M84: 213.6 | N84: 213.6 | O84: 213.6 | P84: 213.6 | Q84: 213.6 | R84: 213.6 | S84: 213.6 | T84: 213.6 | U84: 213.6 | V84: 213.6 | W84: 213.6 | X84: 12.16 | Y84: 112.88 | Z84: 112.88 | AA84: 112.88 | AB84: -125.13 | AC84: 140.12 | AD84: 156.08 | AE84: 156.08 | AF84: 156.08 | AG84: 156.08 | AH84: 212.35 | AI84: 212.35 | AJ84: 245.61 | AK84: 40.66 | AL84: 185.67 | AM84: 185.67 | AN84: 185.67 | AO84: 185.67 | AP84: 185.67 | AQ84: 185.67 | AR84: 185.67 | AS84: 185.67 | AT84: 185.67 | AU84: 185.67 | AV84: 185.67 | AW84: 185.67 | AX84: 185.67 | AY84: 185.67 | AZ84: 185.67 | BA84: 185.67 | BB84: 185.67 | BC84: 156.78 | BD84: 176.04 | BE84: 176.04 | BF84: =SUM(AX84:BE84) -> 1437.21 | BG84: =SUM(AL84:AW84) -> 2228.04 | BH84: =SUM(Z84:AK84) -> 1576.04 | BI84: =SUM(N84:Y84) -> 2261.04 | BJ84: =SUM(BA84:BE84) -> 880.2 | BK84: =SUM(AO84:AZ84) -> 2228.04 | BL84: =SUM(AC84:AN84) -> 2032.42 | BM84: =SUM(Q84:AB84) -> 1720.87 | BN84: =SUM(E84:P84) -> 4047.03 | BO84: =SUM(B84:D84) -> 1357.92
A85: 4816 - Depreciation equipment and furniture | B85: 41.65 | C85: 41.65 | D85: 41.65 | E85: 41.65 | F85: 41.65 | G85: 41.65 | H85: 41.65 | I85: 41.65 | J85: 41.65 | K85: 41.65 | L85: 41.65 | M85: 41.65 | N85: 41.65 | O85: 41.65 | P85: 41.65 | Q85: 41.65 | R85: 41.65 | S85: 41.65 | T85: 41.65 | U85: 41.65 | V85: 41.65 | W85: 41.65 | X85: 41.65 | Y85: 41.65 | Z85: 41.65 | AA85: 41.65 | AC85: 0 | AD85: 13.15 | AE85: 13.15 | AF85: 13.15 | AG85: 13.15 | AH85: 13.15 | AI85: 13.15 | AJ85: 110.55 | AK85: 420.12 | AL85: 512.2 | AM85: 512.2 | AN85: 512.2 | AO85: 512.2 | AP85: 512.2 | AQ85: 512.2 | AR85: 512.2 | AS85: 512.2 | AT85: 512.2 | AU85: 512.2 | AV85: 512.2 | AW85: 512.2 | AX85: 512.2 | AY85: 512.2 | AZ85: 512.2 | BA85: 512.2 | BB85: 512.2 | BC85: 512.2 | BD85: 512.2 | BE85: 512.2 | BF85: =SUM(AX85:BE85) -> 4097.6 | BG85: =SUM(AL85:AW85) -> 6146.4 | BH85: =SUM(Z85:AK85) -> 692.87 | BI85: =SUM(N85:Y85) -> 499.8 | BJ85: =SUM(BA85:BE85) -> 2561 | BK85: =SUM(AO85:AZ85) -> 6146.4 | BL85: =SUM(AC85:AN85) -> 2146.17 | BM85: =SUM(Q85:AB85) -> 458.15 | BN85: =SUM(E85:P85) -> 499.8 | BO85: =SUM(B85:D85) -> 124.95
A86: Total: Depreciation | B86: 494.29 | C86: 494.29 | D86: 494.29 | E86: 494.29 | F86: 494.29 | G86: 494.29 | H86: 494.29 | I86: 494.29 | J86: 563.88 | K86: 275.25 | L86: 275.25 | M86: 275.25 | N86: 275.25 | O86: 275.25 | P86: 275.25 | Q86: =SUM(Q83:Q85) -> 275.25 | R86: =SUM(R83:R85) -> 275.25 | S86: =SUM(S83:S85) -> 1022.91 | T86: =SUM(T83:T85) -> 829.04 | U86: =SUM(U83:U85) -> 865.76 | V86: =SUM(V83:V85) -> 802.41 | W86: =SUM(W83:W85) -> 1002.41 | X86: =SUM(X83:X85) -> 800.97 | ... BE86: =SUM(BE83:BE85) -> 1719.51 | BF86: =SUM(AX86:BE86) -> 13784.97 | BG86: =SUM(AL86:AW86) -> 20749.68 | BH86: =SUM(Z86:AK86) -> 13777.99 | BI86: =SUM(N86:Y86) -> 7601.44 | BJ86: =SUM(BA86:BE86) -> 8597.55 | BK86: =SUM(AO86:AZ86) -> 20749.68 | BL86: =SUM(AC86:AN86) -> 16464.86 | BM86: =SUM(Q86:AB86) -> 9276.24 | BN86: =SUM(E86:P86) -> 4686.83 | BO86: =SUM(B86:D86) -> 1482.87 | BP86: General
A87: Financial Income and Expenses | AO87: 0 | AP87: 0 | AQ87: 0 | AR87: 0 | AS87: 0 | AT87: 0 | AU87: 0 | AV87: 0
A88: 9200 - Interest current account GdW Beheer B.V. | D88: -200.23 | Q88: 0 | AC88: 0 | AD88: 0 | AE88: 0 | AF88: 0 | AG88: 0 | AH88: 0 | AI88: 0 | AJ88: 0 | AK88: 0 | AL88: 0 | AM88: 0 | AN88: 0 | AO88: 0 | AP88: 0 | AQ88: 0 | AR88: 0 | AS88: 0 | AT88: 0 | AU88: 0 | AV88: 0 | AW88: 0 | AX88: 0 | AY88: 0 | AZ88: 0 | BA88: 0 | BF88: =SUM(AX88:BE88) -> 0 | BG88: =SUM(AL88:AW88) -> 0 | BI88: =SUM(N88:Y88) -> 0 | BJ88: =SUM(BA88:BE88) -> 0 | BK88: =SUM(AO88:AZ88) -> 0 | BL88: =SUM(AC88:AN88) -> 0 | BM88: =SUM(Z88:AB88) -> 0 | BN88: =SUM(E88:P88) -> 0 | BO88: =SUM(B88:D88) -> -200.23
A89: 9203 - Interest current account Shanwick B.V. | D89: 0 | G89: -312.81 | H89: -1234.7 | I89: -1300.96 | J89: -1389.97 | K89: -2137.25 | L89: -2443.84 | M89: -2640.93 | N89: -4027.64 | O89: -11525.17 | P89: -5036.84 | Q89: -5462.39 | R89: -6362.03 | S89: -7048.01 | T89: -7100.85 | U89: -7137.39 | V89: -7597.4 | W89: -7984.39 | X89: -9206.28 | Y89: -9486.93 | Z89: -10127.22 | AA89: -10791.9 | AB89: -11615.6 | AC89: -11290 | AD89: -12066.6 | AE89: -12994.7 | AF89: -13953.05 | AG89: -14880.31 | AH89: -17209.76 | AI89: -18420.48 | AJ89: -19041.74 | AK89: -19763.3 | AL89: -19839.53 | AM89: -18027.26 | AN89: -20715.54 | AO89: -17278.26 | AP89: -19205.7 | AQ89: -20715.46 | AR89: -22131.16 | AS89: -22206.34 | AT89: -21733.32 | AU89: -22531.59 | AV89: -21878.84 | AW89: -26079.73 | AX89: -26168.33 | AY89: -23716.21 | AZ89: -23021.86 | BA89: -25563.88 | BB89: -25647.93 | BC89: -24745.95 | BD89: -29134.52 | BE89: -31700.99 | BF89: =SUM(AX89:BE89) -> -209699.67 | BG89: =SUM(AL89:AW89) -> -252342.73 | BH89: =SUM(Z89:AK89) -> -172154.66 | BI89: =SUM(N89:Y89) -> -87975.32 | BJ89: =SUM(BA89:BE89) -> -136793.27 | BK89: =SUM(AO89:AZ89) -> -266666.8 | BL89: =SUM(AC89:AN89) -> -198202.27 | BM89: =SUM(Z89:AB89) -> -32534.72 | BN89: =SUM(E89:P89) -> -32050.11 | BO89: =SUM(B89:D89) -> 0
A90: 9340 - Bank charges | C90: 80.72 | D90: 555.95 | E90: 2694.84 | F90: -604.23 | G90: -689.41 | H90: -337.87 | I90: 708.4 | J90: -694.31 | K90: -706.58 | L90: -700.16 | M90: -647.37 | N90: -678.37 | O90: 7153.25 | P90: 127.98 | Q90: 183.67 | R90: 117.05 | S90: 102.91 | T90: 113.03 | U90: 124.56 | V90: 246.25 | W90: 227.05 | X90: 89.73 | Y90: 189.61 | Z90: 254.77 | AA90: 361.14 | AB90: 204.72 | AC90: 557.49 | AD90: 234.86 | AE90: 380.47 | AF90: 500.81 | AG90: 163.77 | AH90: 228.33 | AI90: 279.77 | AJ90: 187.3 | AK90: 258.45 | AL90: 374.55 | AM90: 178.84 | AN90: 170.38 | AO90: 367.39 | AP90: 265.35 | AQ90: 280.62 | AR90: 371.66 | AS90: 194.98 | AT90: 420.97 | AU90: 315.32 | AV90: 248.22 | AW90: 275.38 | AX90: 194.74 | AY90: 366.6 | AZ90: 282.34 | BA90: 259.53 | BB90: 341.49 | BC90: 336.34 | BD90: 558.87 | BE90: 302.18 | BF90: =SUM(AX90:BE90) -> 2642.09 | BG90: =SUM(AL90:AW90) -> 3463.66 | BH90: =SUM(Z90:AK90) -> 3611.88 | BI90: =SUM(N90:Y90) -> 7996.72 | BJ90: =SUM(BA90:BE90) -> 1798.41 | BK90: =SUM(AO90:AZ90) -> 3583.57 | BL90: =SUM(AC90:AN90) -> 3515.02 | BM90: =SUM(Z90:AB90) -> 820.63 | BN90: =SUM(E90:P90) -> 5626.17 | BO90: =SUM(B90:D90) -> 636.67
A91: 9341 - Interest current account bank | K91: 1012.42 | N91: -133.56 | Q91: -533.71 | T91: -461.97 | W91: -67.49 | Z91: -66.9 | AC91: -61.57 | AD91: 0 | AE91: 0 | AF91: -86.34 | AG91: 0 | AH91: 0 | AI91: -115.95 | AJ91: 0 | AK91: 0 | AL91: -141.98 | AM91: 0 | AN91: 0 | AO91: -134.72 | AP91: 0 | AQ91: 0 | AR91: -156.04 | AS91: 0 | AT91: 0 | AU91: -180.05 | AV91: 0 | AW91: 0 | AX91: -289.7 | AY91: 0 | AZ91: 0 | BA91: -311.64 | BB91: 0 | BC91: 0 | BD91: -331.3 | BE91: 0 | BF91: =SUM(AX91:BE91) -> -932.64 | BG91: =SUM(AL91:AW91) -> -612.79 | BH91: =SUM(Z91:AK91) -> -330.76 | BI91: =SUM(N91:Y91) -> -1196.73 | BJ91: =SUM(BA91:BE91) -> -642.94 | BK91: =SUM(AO91:AZ91) -> -760.51 | BL91: =SUM(AC91:AN91) -> -405.84 | BM91: =SUM(Z91:AB91) -> -66.9 | BN91: =SUM(E91:P91) -> 878.86 | BO91: =SUM(B91:D91) -> 0
A92: 9345 - Interest tax authorities | T92: 366 | AC92: 0 | AD92: 0 | AE92: 0 | AF92: 0 | AG92: 0 | AH92: 0 | AI92: 0 | AJ92: 0 | AK92: 0 | AL92: 0 | AM92: 0 | AN92: 0 | AO92: 0 | AP92: 0 | AQ92: 0 | AR92: 0 | AS92: 167 | AT92: 0 | AU92: 0 | AV92: 0 | AW92: 0 | AX92: 167 | AY92: 0 | AZ92: 0 | BA92: 0 | BF92: =SUM(AX92:BE92) -> 167 | BG92: =SUM(AL92:AW92) -> 167 | BH92: 0 | BI92: =SUM(N92:Y92) -> 366 | BJ92: =SUM(BA92:BE92) -> 0 | BK92: =SUM(AO92:AZ92) -> 334 | BL92: =SUM(AC92:AN92) -> 0 | BM92: =SUM(Z92:AB92) -> 0 | BN92: =SUM(E92:P92) -> 0 | BO92: =SUM(B92:D92) -> 0
A93: 9390 - Payment differences | B93: -2 | D93: 0 | E93: 0.27 | G93: -10.45 | L93: -0.01 | O93: 2.01 | Q93: 4.39 | R93: -1.76 | S93: -2.39 | T93: -2.83 | U93: -0.98 | V93: 16.71 | W93: -147.87 | X93: -9.61 | Y93: 18.46 | Z93: 20 | AA93: 49.89 | AB93: 50.84 | AC93: 0 | AD93: 0 | AE93: 0 | AF93: -10.62 | AG93: 0 | AH93: 0 | AI93: 0 | AJ93: 40 | AK93: 0 | AL93: 31.5 | AM93: 0 | AN93: 0 | AO93: 0 | AP93: 0 | AQ93: 0 | AR93: 0 | AS93: 0 | AT93: 0 | AU93: 0 | AV93: 0 | AW93: 0 | AX93: 0 | AY93: 0 | AZ93: 242.59 | BA93: 0.4 | BB93: 0 | BC93: 0 | BD93: 0 | BE93: 0 | BF93: =SUM(AX93:BE93) -> 242.99 | BG93: =SUM(AL93:AW93) -> 31.5 | BH93: =SUM(Z93:AK93) -> 150.11 | BI93: =SUM(N93:Y93) -> -123.87 | BJ93: =SUM(BA93:BE93) -> 0.4 | BK93: =SUM(AO93:AZ93) -> 242.59 | BL93: =SUM(AC93:AN93) -> 60.88 | BM93: =SUM(Z93:AB93) -> 120.73 | BN93: =SUM(E93:P93) -> -8.18 | BO93: =SUM(B93:D93) -> -2
A94: 9400 - Currency exchange result | E94: -321.38 | J94: 31.8 | M94: -1051.88 | O94: 653.36 | P94: -2.22 | Q94: 31.02 | R94: 4.56 | S94: -33.44 | T94: 45.47 | U94: -643.58 | V94: -3158.75 | W94: 276.36 | X94: 3107.45 | Y94: 1138.99 | Z94: -1970.5 | AA94: -161.44 | AB94: -0.82 | AC94: -76.38 | AD94: -832.01 | AE94: -2028.19 | AF94: 2184.87 | AG94: 3588.59 | AH94: 3170.03 | AI94: -5888.66 | AJ94: -6149.08 | AK94: -5161.05 | AL94: -6938.13 | AM94: 378.1 | AN94: 7311.64 | AO94: 16243.26 | AP94: -744.5 | AQ94: 8307.82 | AR94: -5546.08 | AS94: 6278.01 | AT94: -15507.03 | AU94: 12204.97 | AV94: 225.89 | AW94: 7676.7 | AX94: 6974.5 | AY94: -3684.38 | AZ94: -12761.1 | BA94: 7962.83 | BB94: -2503.82 | BC94: -12143.06 | BD94: 3415.18 | BE94: 5880.06 | BF94: =SUM(AX94:BE94) -> -6859.79 | BG94: =SUM(AL94:AW94) -> 29890.65 | BH94: =SUM(Z94:AK94) -> -13324.64 | BI94: =SUM(N94:Y94) -> 1419.22 | BJ94: =SUM(BA94:BE94) -> 2611.19 | BK94: =SUM(AO94:AZ94) -> 19668.06 | BL94: =SUM(AC94:AN94) -> -10440.27 | BM94: =SUM(Z94:AB94) -> -2132.76 | BN94: =SUM(E94:P94) -> -690.32 | BO94: =SUM(B94:D94) -> 0
A95: 9410 - Purchase discounts | N95: -54.01 | AC95: 0 | AD95: 0 | AE95: 0 | AF95: 0 | AG95: 0 | AH95: 0 | AI95: 0 | AJ95: 0 | AK95: 0 | AL95: 0 | AM95: 0 | AN95: 0 | AO95: 0 | AP95: 0 | AQ95: 0 | AR95: 0 | AS95: 0 | AT95: 0 | AU95: 0 | AV95: 0 | AW95: 0 | AX95: 0 | AY95: 0 | AZ95: 0 | BA95: 0 | BF95: =SUM(AX95:BE95) -> 0 | BG95: =SUM(AL95:AW95) -> 0 | BI95: =SUM(N95:Y95) -> -54.01 | BJ95: =SUM(BA95:BE95) -> 0 | BK95: =SUM(AO95:AZ95) -> 0 | BL95: =SUM(AC95:AN95) -> 0 | BM95: =SUM(Z95:AB95) -> 0 | BN95: =SUM(E95:P95) -> -54.01 | BO95: =SUM(B95:D95) -> 0
A96: 9420 - Performance bond result | AC96: 0 | AD96: -1218.51 | AE96: 0 | AF96: 0 | AG96: 0 | AH96: 0 | AI96: 0 | AJ96: 0 | AK96: 0 | AL96: 0 | AM96: 0 | AN96: 0 | AO96: 0 | AP96: 0 | AQ96: 0 | AR96: 0 | AS96: 0 | AT96: 0 | AU96: 0 | AV96: 0 | AW96: 0 | AX96: 0 | AY96: 0 | AZ96: 0 | BA96: 0 | BF96: =SUM(AX96:BE96) -> 0 | BG96: =SUM(AL96:AW96) -> 0 | BH96: =SUM(Z96:AK96) -> -1218.51 | BJ96: =SUM(BA96:BE96) -> 0 | BK96: =SUM(AO96:AZ96) -> 0 | BL96: =SUM(AC96:AN96) -> -1218.51
A97: Total: Financial Income and Expenses | B97: -2 | C97: 80.72 | D97: =SUM(D88:D95) -> 355.72 | E97: 2373.73 | F97: -604.23 | G97: -1012.67 | H97: -1572.57 | I97: -592.56 | J97: -2052.48 | K97: -1831.41 | L97: -3144.01 | M97: -4340.18 | N97: -4893.58 | O97: -3716.55 | P97: -4911.08 | Q97: =SUM(Q88:Q95) -> -5777.02 | R97: =SUM(R88:R95) -> -6242.18 | S97: =SUM(S88:S95) -> -6980.93 | T97: =SUM(T88:T95) -> -7041.15 | U97: =SUM(U88:U95) -> -7657.39 | V97: =SUM(V88:V95) -> -10493.19 | W97: =SUM(W88:W95) -> -7696.34 | X97: =SUM(X88:X95) -> -6018.71 | ... AC97: =SUM(AC88:AC95) -> -10870.46 | AD97: =SUM(AD88:AD96) -> -13882.26 | AE97: =SUM(AE88:AE96) -> -14642.42 | AF97: =SUM(AF88:AF96) -> -11364.33 | AG97: =SUM(AG88:AG96) -> -11127.95 | AH97: =SUM(AH88:AH96) -> -13811.4 | AI97: =SUM(AI88:AI96) -> -24145.32 | AJ97: =SUM(AJ88:AJ96) -> -24963.52 | AK97: =SUM(AK88:AK96) -> -24665.9 | ... BE97: =SUM(BE88:BE96) -> -25518.75 | BF97: =SUM(AX97:BE97) -> -214440.02 | BG97: =SUM(AL97:AW97) -> -219402.71 | BH97: =SUM(Z97:AK97) -> -183266.58 | BI97: =SUM(N97:Y97) -> -79567.99 | BJ97: =SUM(BA97:BE97) -> -133026.21 | BK97: =SUM(AO97:AZ97) -> -243599.09 | BL97: =SUM(AC97:AN97) -> -206690.99 | BM97: =SUM(Q97:AB97) -> -99839.8 | BN97: =SUM(E97:P97) -> -26297.59 | BO97: =SUM(B97:D97) -> 434.44 | BP97: Interest
A98: Taxes
A99: 9800 - Corporate income tax | B99: 26226 | C99: 24756 | D99: 26296 | E99: 28215 | F99: 32825 | G99: 24693 | H99: 25692 | I99: 54349.17 | J99: 48534.96 | K99: 56290.24 | L99: 48749.24 | M99: 54887.83 | N99: 56382.34 | O99: 37071.24 | P99: 48106.74 | Q99: 39876.47 | R99: 55860.56 | S99: 25065.99 | T99: 41580.88 | U99: 45665.95 | V99: 37496.42 | W99: 55103.58 | X99: 58847.98 | Y99: 54092.96 | Z99: 46642.94 | AA99: 37812.83 | AB99: 41784.02 | AC99: 43114.36 | AD99: 55839.87 | AE99: 42829.52 | AF99: 32034.45 | AG99: 80242.11 | AH99: 86706 | AI99: 75262.12 | AJ99: 66265 | AK99: 63229 | AL99: 71734.72 | AM99: 54664 | AN99: 87840 | AO99: 68950 | AP99: 81605 | AQ99: 26394 | AR99: 78720 | AS99: 85833 | AT99: 78748.41 | AU99: 107561.76 | AV99: 88185.99 | AW99: 86825.82 | AX99: 67432.36 | AY99: 78280 | AZ99: 93100 | BA99: 55989.59 | BB99: 95749.66 | BC99: 87208.29 | BD99: 86591.9 | BE99: 86093.95 | BF99: =SUM(AX99:BE99) -> 650445.75 | BG99: =SUM(AL99:AW99) -> 917062.7 | BH99: =SUM(Z99:AK99) -> 671762.22 | BI99: =SUM(N99:Y99) -> 555151.11 | BJ99: =SUM(BA99:BE99) -> 411633.39 | BK99: =SUM(AO99:AZ99) -> 941636.34 | BL99: =SUM(AC99:AN99) -> 759761.15 | BM99: =SUM(Q99:AB99) -> 539830.58 | BN99: =SUM(E99:P99) -> 515796.76 | BO99: =SUM(B99:D99) -> 77278
A100: Total: Taxes | B100: 26226 | C100: 24756 | D100: 26296 | E100: 28215 | F100: 32825 | G100: 24693 | H100: 25692 | I100: 54349.17 | J100: 48534.96 | K100: 56290.24 | L100: 48749.24 | M100: 54887.83 | N100: 56382.34 | O100: 37071.24 | P100: 48406.74 | Q100: 39876.47 | R100: 55860.56 | S100: 25065.99 | T100: =T99 -> 41580.88 | U100: =U99 -> 45665.95 | V100: =V99 -> 37496.42 | W100: =W99 -> 55103.58 | X100: =X99 -> 58847.98 | Y100: =Y99 -> 54092.96 | Z100: =Z99 -> 46642.94 | AA100: =AA99 -> 37812.83 | ... BE100: =BE99 -> 86093.95 | BF100: =SUM(AX100:BE100) -> 650445.75 | BG100: =SUM(AL100:AW100) -> 917062.7 | BH100: =SUM(Z100:AK100) -> 671762.22 | BI100: =SUM(N100:Y100) -> 555451.11 | BJ100: =SUM(BA100:BE100) -> 411633.39 | BK100: =SUM(AO100:AZ100) -> 941636.34 | BL100: =SUM(AC100:AN100) -> 759761.15 | BM100: =SUM(Q100:AB100) -> 539830.58 | BN100: =SUM(E100:P100) -> 516096.76 | BO100: =SUM(B100:D100) -> 77278 | BP100: Taxes
A101: Total: Operating costs | B101: 109390.89 | C101: 110115.45 | D101: 112944.38 | E101: 113442.07 | F101: 120238.86 | G101: 162808 | H101: 138912.58 | I101: 158678.48 | J101: 149551.91 | K101: 167294.76 | L101: 188425.98 | M101: 190255.54 | N101: 195144.6 | O101: 137713.18 | P101: 217013.55 | Q101: =SUM(Q45,Q51,Q60,Q63,Q74,Q81,Q86,Q97,Q100) -> 154740.2 | R101: =SUM(R45,R51,R60,R63,R74,R81,R86,R97,R100) -> 186275.5 | S101: =SUM(S45,S51,S60,S63,S74,S81,S86,S97,S100) -> 236978.55 | T101: =SUM(T45,T51,T60,T63,T74,T81,T86,T97,T100) -> 178543.95 | U101: =SUM(U45,U51,U60,U63,U74,U81,U86,U97,U100) -> 177950.34 | V101: =SUM(V45,V51,V60,V63,V74,V81,V86,V97,V100) -> 171591.93 | W101: =SUM(W45,W51,W60,W63,W74,W81,W86,W97,W100) -> 179975.49 | X101: =SUM(X45,X51,X60,X63,X74,X81,X86,X97,X100) -> 191750.18 | ... BE101: =SUM(BE45,BE51,BE60,BE63,BE74,BE81,BE86,BE97,BE100) -> 386060.85 | BF101: =SUM(AX101:BE101) -> 2953442.4 | BG101: =SUM(AL101:AW101) -> 4065810.7 | BH101: =SUM(Z101:AK101) -> 3226012 | BI101: =SUM(N101:Y101) -> 2252094.7 | BJ101: =SUM(BA101:BE101) -> 1910625.7 | BK101: =SUM(AO101:AZ101) -> 4185868.4 | BL101: =SUM(AC101:AN101) -> 3469733.2 | BM101: =SUM(Q101:AB101) -> 2381261.2 | BN101: =SUM(E101:P101) -> 1939479.5 | BO101: =SUM(B101:D101) -> 332450.72
A102: Result | B102: =-SUM(B23,B101) -> 146959.54 | C102: =-SUM(C23,C101) -> 139551.79 | D102: =-SUM(D23,D101) -> 168410.91 | E102: =-SUM(E23,E101) -> 172606.93 | F102: =-SUM(F23,F101) -> 187948.24 | G102: =-SUM(G23,G101) -> 141701.3 | H102: =-SUM(H23,H101) -> 175196.08 | I102: =-SUM(I23,I101) -> 159364.08 | ... BE102: =-SUM(BE23,BE101) -> 261361.74 | BF102: =SUM(AX102:BE102) -> 1969796.8 | BG102: =SUM(AL102:AW102) -> 2674057.2 | BH102: =SUM(Z102:AK102) -> 2241362.3 | BI102: =SUM(N102:Y102) -> 2127309.5 | BJ102: =SUM(BA102:BE102) -> 1283783.6 | BK102: =SUM(AO102:AZ102) -> 2759347.8 | BL102: =SUM(AC102:AN102) -> 2274121.7 | BM102: =SUM(Q102:AB102) -> 2292654.4 | BN102: =SUM(E102:P102) -> 1825865.3 | BO102: =SUM(B102:D102) -> 454922.24
A103: Total: Profit and loss statement
...

Sheet Budget - Overview
A3: 1 | B3: Revenue | D3: Apr | E3: May | F3: Jun | G3: Jul | H3: Aug | I3: Sept | J3: Oct | K3: Nov | L3: Dec | M3: Jan | N3: Feb | O3: Mar | P3: Total | T3: Actual | U3: Actual | V3: Actual | W3: Actual | X3: Budget
B4: Actual | C4: FY 24/25 | D4: ='P&L WACD'!AC6 -> 0.074676379 | E4: ='P&L WACD'!AD6 -> 0.081064474 | F4: ='P&L WACD'!AE6 -> 0.079698561 | G4: ='P&L WACD'!AF6 -> 0.082174781 | H4: ='P&L WACD'!AG6 -> 0.080414804 | I4: ='P&L WACD'!AH6 -> 0.081936249 | J4: ='P&L WACD'!AI6 -> 0.084780069 | K4: ='P&L WACD'!AJ6 -> 0.086797608 | ... O4: ='P&L WACD'!AN6 -> 0.087963471 | P4: =SUM(D4:O4) -> 1 | T4: FY 22/23 | U4: FY 23/24 | V4: FY 24/25 | W4: FY25/26 | X4: FY26/27
B5: Actual | C5: FY 25/26 | D5: ='P&L WACD'!AO6 -> 0.075923013 | E5: ='P&L WACD'!AP6 -> 0.07748022 | F5: ='P&L WACD'!AQ6 -> 0.078177321 | G5: ='P&L WACD'!AR6 -> 0.073821908 | H5: ='P&L WACD'!AS6 -> 0.080140305 | I5: ='P&L WACD'!AT6 -> 0.086795626 | J5: ='P&L WACD'!AU6 -> 0.093264005 | K5: ='P&L WACD'!AV6 -> 0.088356974 | ... O5: ='P&L WACD'!AZ6 -> 0.092860354 | P5: =SUM(D5:O5) -> 1 | S5: Revenue | T5: 3805685 | U5: 4754476.6 | V5: =-SUM('P&L WACD'!AC19:AN19) -> 5896558.4 | W5: =-SUM('P&L WACD'!AO19:AZ19) -> 7036925.6 | X5: =X6+W5 -> 7786925.6
C6: Average | D6: =AVERAGE(D4:D5) -> 0.075299696 | E6: =AVERAGE(E4:E5) -> 0.079272347 | F6: =AVERAGE(F4:F5) -> 0.078937941 | G6: =AVERAGE(G4:G5) -> 0.077998344 | H6: =AVERAGE(H4:H5) -> 0.080277554 | I6: =AVERAGE(I4:I5) -> 0.084365937 | J6: =AVERAGE(J4:J5) -> 0.089022037 | K6: =AVERAGE(K4:K5) -> 0.087577291 | ... O6: =AVERAGE(O4:O5) -> 0.090411913 | P6: =SUM(D6:O6) -> 1 | S6: Revenue growth abs. | U6: =U5-T5 -> 948791.61 | V6: =V5-U5 -> 1142081.8 | W6: =W5-V5 -> 1140367.1 | X6: 750000
S7: Revenue growth % | U7: =U5/T5-1 -> 0.24930902 | V7: =V5/U5-1 -> 0.2402119 | W7: =W5/V5-1 -> 0.19339537 | X7: =X5/W5-1 -> 0.10658064
B8: Budget | C8: FY 26/27 | D8: =$X$5*D6 -> 586353.13 | E8: =$X$5*E6 -> 617287.87 | F8: =$X$5*F6 -> 614683.87 | G8: =$X$5*G6 -> 607367.3 | H8: =$X$5*H6 -> 625115.34 | I8: =$X$5*I6 -> 656951.28 | J8: =$X$5*J6 -> 693207.97 | K8: =$X$5*K6 -> 681957.85 | ... O8: =$X$5*O6 -> 704030.84 | P8: =SUM(D8:O8) -> 7786925.6
B9: Actual | C9: FY 26/27 | D9: =-'P&L WACD'!BA19 -> 617842.09 | E9: =-'P&L WACD'!BB19 -> 649472.9 | F9: =-'P&L WACD'!BC19 -> 679312.86 | G9: =-'P&L WACD'!BD19 -> 629471.91 | H9: =-'P&L WACD'!BE19 -> 640793.23 | S9: Cost | T9: =T5-T11 -> 1490020.5 | U9: =U5-U11 -> 2021831.4 | V9: =V5-V11 -> 3069366.6 | W9: =W5-W11 -> 3579540.5 | X9: =X5-X11 -> 4282809.1
B10: Actual vs Budget % | D10: =D9/D8-1 -> 0.053703073 | E10: =E9/E8-1 -> 0.052139424 | F10: =F9/F8-1 -> 0.10514183 | G10: =G9/G8-1 -> 0.036394134 | H10: =H9/H8-1 -> 0.025079995
B11: Actual vs Budget % - Ytd | E11: =SUM(D9:E9)/SUM(D8:E8)-1 -> 0.052901155 | F11: =SUM(E9:F9)/SUM(E8:F8)-1 -> 0.078584614 | G11: =SUM(F9:G9)/SUM(F8:G8)-1 -> 0.070973785 | H11: =SUM(G9:H9)/SUM(G8:H8)-1 -> 0.030655601 | S11: EBIT | T11: 2315664.5 | U11: =SUM('P&L WACD'!Q105:AB105) -> 2732645.2 | V11: =SUM('P&L WACD'!AC105:AN105) -> 2827191.8 | W11: =SUM('P&L WACD'!AO105:AZ105) -> 3457385 | X11: =+X5*X15 -> 3504116.5
B12: Actual YoY % - Ytd | E12: =SUM(D9:E9)/SUM('P&L WACD'!AO19:AP19)*-1-1 -> 0.17399731 | F12: =SUM(E9:F9)/SUM('P&L WACD'!AP19:AQ19)*-1-1 -> 0.21311464 | G12: =SUM(F9:G9)/SUM('P&L WACD'!AQ19:AR19)*-1-1 -> 0.22361246 | H12: =SUM(G9:H9)/SUM('P&L WACD'!AR19:AS19)*-1-1 -> 0.17245796 | S12: EBIT growth abs | U12: =U11-T11 -> 416980.73 | V12: =V11-U11 -> 94546.6 | W12: =W11-V11 -> 630193.2 | X12: =X11-W11 -> 46731.486
A13: 2 | B13: Cost | D13: Apr | E13: May | F13: Jun | G13: Jul | H13: Aug | I13: Sept | J13: Oct | K13: Nov | L13: Dec | M13: Jan | N13: Feb | O13: Mar | P13: Total | S13: EBIT growth % | U13: =U11/T11-1 -> 0.18006958 | V13: =V11/U11-1 -> 0.03459893 | W13: =W11/V11-1 -> 0.2229043 | X13: =X11/W11-1 -> 0.013516425
B14: Actual | C14: FY 24/25 | D14: ='P&L WACD'!AC108 -> 0.067360135 | E14: ='P&L WACD'!AD108 -> 0.062651167 | F14: ='P&L WACD'!AE108 -> 0.080061071 | G14: ='P&L WACD'!AF108 -> 0.089004864 | H14: ='P&L WACD'!AG108 -> 0.10320827 | I14: ='P&L WACD'!AH108 -> 0.07738101 | J14: ='P&L WACD'!AI108 -> 0.099789985 | K14: ='P&L WACD'!AJ108 -> 0.085365895 | ... O14: ='P&L WACD'!AN108 -> 0.083655924 | P14: =SUM(D14:O14) -> 1
B15: Actual | C15: FY 25/26 | D15: ='P&L WACD'!AO108 -> 0.062464469 | E15: ='P&L WACD'!AP108 -> 0.069652257 | F15: ='P&L WACD'!AQ108 -> 0.1274614 | G15: ='P&L WACD'!AR108 -> 0.068272835 | H15: ='P&L WACD'!AS108 -> 0.070301263 | I15: ='P&L WACD'!AT108 -> 0.090839801 | J15: ='P&L WACD'!AU108 -> 0.071909192 | K15: ='P&L WACD'!AV108 -> 0.081915829 | ... O15: ='P&L WACD'!AZ108 -> 0.091460922 | P15: =SUM(D15:O15) -> 1 | S15: EBIT as % of T/o | T15: =+T11/T5 -> 0.60847508 | U15: =+U11/U5 -> 0.57475206 | V15: =+V11/V5 -> 0.47946473 | W15: =+W11/W5 -> 0.49132039 | X15: 0.45
C16: Average | D16: =AVERAGE(D14:D15) -> 0.064912302 | E16: =AVERAGE(E14:E15) -> 0.066151712 | F16: =AVERAGE(F14:F15) -> 0.10376124 | G16: =AVERAGE(G14:G15) -> 0.07863885 | H16: =AVERAGE(H14:H15) -> 0.086754766 | I16: =AVERAGE(I14:I15) -> 0.084110405 | J16: =AVERAGE(J14:J15) -> 0.085849589 | K16: =AVERAGE(K14:K15) -> 0.083640862 | ... O16: =AVERAGE(O14:O15) -> 0.087558423 | P16: =SUM(D16:O16) -> 1
B18: Budget | C18: FY 26/27 | D18: =$X$9*D16 -> 278007 | E18: =$X$9*E16 -> 283315.15 | F18: =$X$9*F16 -> 444389.57 | G18: =$X$9*G16 -> 336795.18 | H18: =$X$9*H16 -> 371554.1 | I18: =$X$9*I16 -> 360228.81 | J18: =$X$9*J16 -> 367677.4 | K18: =$X$9*K16 -> 358217.84 | ... O18: =$X$9*O16 -> 374996.01 | P18: =SUM(D18:O18) -> 4282809.1
B19: Actual | C19: FY 26/27 | D19: ='P&L WACD'!AO107 -> 223594.1 | E19: ='P&L WACD'!AP107 -> 249323.08 | F19: ='P&L WACD'!AQ107 -> 456253.26 | G19: ='P&L WACD'!AR107 -> 244385.38 | H19: ='P&L WACD'!AS107 -> 251646.22
B20: Actual vs Budget % | D20: =D19/D18-1 -> -0.19572492 | E20: =E19/E18-1 -> -0.11997972 | F20: =F19/F18-1 -> 0.026696606 | G20: =G19/G18-1 -> -0.27437981 | H20: =H19/H18-1 -> -0.32271984
A23: 3 | B23: EBIT
B24: Budget | C24: FY 26/27 | D24: =D8-D18 -> 308346.13 | E24: =E8-E18 -> 333972.71 | F24: =F8-F18 -> 170294.3 | G24: =G8-G18 -> 270572.13 | H24: =H8-H18 -> 253561.24 | I24: =I8-I18 -> 296722.47 | J24: =J8-J18 -> 325530.58 | K24: =K8-K18 -> 323740.01 | ... O24: =O8-O18 -> 329034.83 | P24: =SUM(D24:O24) -> 3504116.5
B25: Actual | C25: FY 26/27 | D25: =D9-D19 -> 394247.99 | E25: =E9-E19 -> 400149.82 | F25: =F9-F19 -> 223059.6 | G25: =G9-G19 -> 385086.53 | H25: =H9-H19 -> 389147.01
B26: Actual vs Budget % | D26: =D25/D24-1 -> 0.27858907 | E26: =E25/E24-1 -> 0.19815124 | F26: =F25/F24-1 -> 0.30984769 | G26: =G25/G24-1 -> 0.42323061 | H26: =H25/H24-1 -> 0.53472593
A28: 4 | B28: EBIT Margin
B29: Budget | C29: FY 26/27 | D29: =D24/D8 -> 0.52587104 | E29: =E24/E8 -> 0.54103236 | F29: =F24/F8 -> 0.27704372 | G29: =G24/G8 -> 0.44548352 | H29: =H24/H8 -> 0.40562313
B30: Actual | C30: FY 26/27 | D30: =D25/D9 -> 0.63810478 | E30: =E25/E9 -> 0.61611473 | F30: =F25/F9 -> 0.32836063 | G30: =G25/G9 -> 0.61176126 | H30: =H25/H9 -> 0.60728952

Sheet Budget - Ken
B3: Revenue | D3: Apr | E3: May | F3: Jun | G3: Jul | H3: Aug | I3: Sep | J3: Oct | K3: Nov | L3: Dec | M3: Jan | N3: Feb | O3: Mar | P3: Total | T3: Actual | U3: Actual | V3: Estimate | W3: Budget | X3: Budget
B4: Actual | C4: FY 24/25 | D4: 0.074676379 | E4: 0.081064474 | F4: 0.079698561 | G4: 0.082174781 | H4: 0.080414804 | I4: 0.081936249 | J4: 0.084780069 | K4: 0.086797608 | L4: 0.089111249 | M4: 0.090038509 | N4: 0.081343846 | O4: 0.087963471 | P4: =SUM(D4:O4) -> 1 | T4: FY 23/24 | U4: FY 24/25 | V4: FY 25/26 | W4: FY 26/27 | X4: FY 25/26
B5: Actual | C5: FY 25/26 | D5: 0.076332074 | E5: 0.077897671 | F5: 0.078598529 | G5: 0.074219649 | H5: 0.080572089 | I5: 0.087263268 | J5: 0.093766497 | K5: 0.088833028 | L5: 0.091821726 | M5: 0.081444078 | N5: 0.081278568 | O5: 0.087972824 | P5: =SUM(D5:O5) -> 1 | S5: Revenue | T5: 4754476.6 | U5: 5896558.4 | V5: 6999214.9 | W5: 7749214.9 | X5: 6546558.4
C6: Average | D6: =(D4+D5)/2 -> 0.075504226 | E6: =(E4+E5)/2 -> 0.079481073 | F6: =(F4+F5)/2 -> 0.079148545 | G6: =(G4+G5)/2 -> 0.078197215 | H6: =(H4+H5)/2 -> 0.080493446 | I6: =(I4+I5)/2 -> 0.084599758 | J6: =(J4+J5)/2 -> 0.089273283 | K6: =(K4+K5)/2 -> 0.087815318 | ... O6: =(O4+O5)/2 -> 0.087968148 | P6: =SUM(D6:O6) -> 1 | S6: Revenue growth abs. | U6: =U5-T5 -> 1142081.8 | V6: =V5-U5 -> 1102656.4 | W6: =W5-V5 -> 750000
S7: Revenue growth % | U7: =U6/T5 -> 0.2402119 | V7: =V6/U5 -> 0.187 | W7: =W6/V5 -> 0.10715488
B8: Budget | C8: FY 26/27 | D8: =D6*P8 -> 585098.47 | E8: =E6*P8 -> 615915.91 | F8: =F6*P8 -> 613339.08 | G8: =G6*P8 -> 605967.02 | H8: =H6*P8 -> 623761.01 | I8: =I6*P8 -> 655581.7 | J8: =J6*P8 -> 691797.85 | K8: =K6*P8 -> 680499.77 | L8: =L6*P8 -> 701044.25 | M8: =M6*P8 -> 664427.71 | N8: =N6*P8 -> 630098.01 | O8: =O6*P8 -> 681684.08 | P8: 7749214.9
S9: Cost | T9: 2021831.4 | U9: 3069366.6 | V9: 3562600.4 | W9: 4262068.2 | X9: 3969366.6
S11: EBIT | T11: 2732645.2 | U11: 2827191.8 | V11: 3436614.5 | W11: 3487146.7 | X11: 2577191.8
S12: EBIT growth abs | U12: =U11-T11 -> 94546.6 | V12: =V11-U11 -> 609422.68
B13: Cost | D13: Apr | E13: May | F13: Jun | G13: Jul | H13: Aug | I13: Sep | J13: Oct | K13: Nov | L13: Dec | M13: Jan | N13: Feb | O13: Mar | P13: Total | S13: EBIT growth % | U13: =U12/T11 -> 0.03459893 | V13: =V12/U11 -> 0.2155576
B14: Actual | C14: FY 24/25 | D14: 0.067360135 | E14: 0.062651167 | F14: 0.080061071 | G14: 0.089004864 | H14: 0.10320827 | I14: 0.07738101 | J14: 0.099789985 | K14: 0.085365895 | L14: 0.083821557 | M14: 0.091358969 | N14: 0.076341151 | O14: 0.083655924 | P14: =SUM(D14:O14) -> 1
B15: Actual | C15: FY 25/26 | D15: 0.062761488 | E15: 0.069983454 | F15: 0.12806748 | G15: 0.068597472 | H15: 0.070635545 | I15: 0.091271744 | J15: 0.072251121 | K15: 0.082305339 | L15: 0.092511215 | M15: 0.091884771 | N15: 0.082385522 | O15: 0.087344845 | P15: =SUM(D15:O15) -> 1 | S15: EBIT margin | T15: =T11/T5 -> 0.57475206 | U15: =U11/U5 -> 0.47946473 | V15: =V11/V5 -> 0.491 | W15: =W11/W5 -> 0.45
C16: Average | D16: =(D14+D15)/2 -> 0.065060811 | E16: =(E14+E15)/2 -> 0.066317311 | F16: =(F14+F15)/2 -> 0.10406428 | G16: =(G14+G15)/2 -> 0.078801168 | H16: =(H14+H15)/2 -> 0.086921908 | I16: =(I14+I15)/2 -> 0.084326377 | J16: =(J14+J15)/2 -> 0.086020553 | K16: =(K14+K15)/2 -> 0.083835617 | ... O16: =(O14+O15)/2 -> 0.085500385 | P16: =SUM(D16:O16) -> 1
B18: Budget | C18: FY 26/27 | D18: =D16*P18 -> 277293.61 | E18: =E16*P18 -> 282648.9 | F18: =F16*P18 -> 443529.04 | G18: =G16*P18 -> 335855.95 | H18: =H16*P18 -> 370467.1 | I18: =I16*P18 -> 359404.77 | J18: =J16*P18 -> 366625.46 | K18: =K16*P18 -> 357313.12 | L18: =L16*P18 -> 375771.15 | M18: =M16*P18 -> 390498.66 | N18: =N16*P18 -> 338251.95 | O18: =O16*P18 -> 364408.47 | P18: 4262068.2
B23: EBIT | D23: Apr | E23: May | F23: Jun | G23: Jul | H23: Aug | I23: Sep | J23: Oct | K23: Nov | L23: Dec | M23: Jan | N23: Feb | O23: Mar | P23: Total
B24: Budget | C24: FY 26/27 | D24: =D8-D18 -> 307804.86 | E24: =E8-E18 -> 333267.01 | F24: =F8-F18 -> 169810.04 | G24: =G8-G18 -> 270111.07 | H24: =H8-H18 -> 253293.91 | I24: =I8-I18 -> 296176.94 | J24: =J8-J18 -> 325172.39 | K24: =K8-K18 -> 323186.65 | ... O24: =O8-O18 -> 317275.61 | P24: =SUM(D24:O24) -> 3487146.7
B28: EBIT Margin
B29: Budget | C29: FY 26/27 | D29: =D24/D8 -> 0.5260736 | E29: =E24/E8 -> 0.54109174 | F29: =F24/F8 -> 0.2768616 | G29: =G24/G8 -> 0.4457521 | H29: =H24/H8 -> 0.40607526 | I29: =I24/I8 -> 0.4517773 | J29: =J24/J8 -> 0.47003961 | K29: =K24/K8 -> 0.47492544 | ... P29: =P24/P8 -> 0.45

Sheet Budget - Int & Taxes
A1: Row Labels | B1: Sum of 20244 | C1: Sum of 20245 | D1: Sum of 20246 | E1: Sum of 20247 | F1: Sum of 20248 | G1: Sum of 20249 | H1: Sum of 202410 | I1: Sum of 202411 | J1: Sum of 202412 | K1: Sum of 2025 | L1: Sum of 20252 | M1: Sum of 20253 | N1: Total | O1: % | P1: T/o | Q1: Monthly Avg
A2: Interest | B2: -10870.46 | C2: -13882.26 | D2: -14642.42 | E2: -11364.33 | F2: -11127.95 | G2: -13811.4 | H2: -24145.32 | I2: -24963.52 | J2: -24665.9 | K2: -26513.59 | L2: -17470.32 | M2: -13233.52 | N2: =SUM(B2:M2) -> -206690.99 | Q2: =+N2/12 -> -17224.249
A3: Taxes | B3: 43114.36 | C3: 55839.87 | D3: 42829.52 | E3: 32034.45 | F3: 80242.11 | G3: 86706 | H3: 75262.12 | I3: 66265 | J3: 63229 | K3: 71734.72 | L3: 54664 | M3: 87840 | N3: =SUM(B3:M3) -> 759761.15 | O3: =+N3/P3 -> 0.12884824 | P3: 5896558.4
A4: Grand Total | B4: 32243.9 | C4: 41957.61 | D4: 28187.1 | E4: 20670.12 | F4: 69114.16 | G4: 72894.6 | H4: 51116.8 | I4: 41301.48 | J4: 38563.1 | K4: 45221.13 | L4: 37193.68 | M4: 74606.48 | N4: =SUM(B4:M4) -> 553070.16
N5: =SUM(N2:N4) -> 1106140.3
A7: Row Labels | B7: Sum of 20254 | C7: Sum of 20255 | D7: Sum of 20256 | E7: Sum of 20257 | F7: Sum of 20258 | G7: Sum of 20259 | H7: Sum of 202510 | I7: Sum of 202511 | J7: Sum of 202512 | K7: Sum of 2026 | L7: Sum of 20262 | M7: Sum of 20263
A8: Interest | B8: -802.33 | C8: -19684.85 | D8: -12127.02 | E8: -27461.62 | F8: -15566.35 | G8: -36819.38 | H8: -10191.35 | I8: -21404.73 | J8: -18127.65 | K8: -19121.79 | L8: -27033.99 | M8: -35258.03 | N8: =SUM(B8:M8) -> -243599.09 | Q8: =+N8/12 -> -20299.924
A9: Taxes | B9: 68950 | C9: 81605 | D9: 26394 | E9: 78720 | F9: 85833 | G9: 78748.41 | H9: 107561.76 | I9: 88185.99 | J9: 86825.82 | K9: 67432.36 | L9: 78280 | M9: 93100 | N9: =SUM(B9:M9) -> 941636.34 | O9: =+N9/P9 -> 0.1338136 | P9: 7036925.6
A10: Grand Total | B10: 68147.67 | C10: 61920.15 | D10: 14266.98 | E10: 51258.38 | F10: 70266.65 | G10: 41929.03 | H10: 97370.41 | I10: 66781.26 | J10: 68698.17 | K10: 48310.57 | L10: 51246.01 | M10: 57841.97 | N10: =SUM(B10:M10) -> 698037.25
N11: =SUM(N8:N10) -> 1396074.5
Q12: =+AVERAGE(Q8,Q2) -> -18762.087
O14: Tax is budgeted @ 13%

Sheet Budget - Cost
A1: Row Labels | B1: Sum of 20244 | C1: Sum of 20245 | D1: Sum of 20246 | E1: Sum of 20247 | F1: Sum of 20248 | G1: Sum of 20249 | H1: Sum of 202410 | I1: Sum of 202411 | J1: Sum of 202412 | K1: Sum of 2025 | L1: Sum of 20252 | M1: Sum of 20253
A2: COGS | B2: 7155.9 | C2: 6655.11 | D2: 36583.34 | E2: 25780.1 | F2: 5822.75 | G2: 6136.45 | H2: 55014.13 | I2: 1860.7 | J2: 1929.01 | K2: 1934.88 | L2: 2029.5 | M2: 1801.75 | N2: =SUM(B2:M2) -> 152703.62
A3: General | B3: 62587.98 | C3: 61042.19 | D3: 68117.71 | E3: 98716.81 | F3: 72232.84 | G3: 78966.48 | H3: 93031.85 | I3: 110141.24 | J3: 104418.4 | K3: 118511.42 | L3: 76889.94 | M3: 91340.87 | N3: =SUM(B3:M3) -> 1035997.7
A4: Personnel | B4: 137009.07 | C4: 124602.1 | D4: 141035.73 | E4: 148691.65 | F4: 238728.43 | G4: 152407.76 | H4: 158246.07 | I4: 150017.29 | J4: 150931.68 | K4: 159967.87 | L4: 155399.54 | M4: 163628.08 | N4: =SUM(B4:M4) -> 1880665.3
A5: Grand Total | B5: 206752.95 | C5: 192299.4 | D5: 245736.78 | E5: 273188.56 | F5: 316784.02 | G5: 237510.69 | H5: 306292.05 | I5: 262019.23 | J5: 257279.09 | K5: 280414.17 | L5: 234318.98 | M5: 256770.7 | N5: =SUM(N2:N4) -> 3069366.6
A7: FY 24/25
A8: COGS | B8: =+B2/B$5 -> 0.034610873 | C8: =+C2/C$5 -> 0.034608064 | D8: =+D2/D$5 -> 0.14887206 | E8: =+E2/E$5 -> 0.094367422 | F8: =+F2/F$5 -> 0.01838082 | G8: =+G2/G$5 -> 0.025836521 | H8: =+H2/H$5 -> 0.17961331 | I8: =+I2/I$5 -> 0.0071013872 | ... N8: =+N2/N$5 -> 0.049750857
A9: General | B9: =+B3/B$5 -> 0.30271868 | C9: =+C3/C$5 -> 0.31743308 | D9: =+D3/D$5 -> 0.27719786 | E9: =+E3/E$5 -> 0.36135045 | F9: =+F3/F$5 -> 0.2280192 | G9: =+G3/G$5 -> 0.33247548 | H9: =+H3/H$5 -> 0.30373576 | I9: =+I3/I$5 -> 0.42035556 | ... N9: =+N3/N$5 -> 0.33752818
A10: Personnel | B10: =+B4/B$5 -> 0.66267045 | C10: =+C4/C$5 -> 0.64795886 | D10: =+D4/D$5 -> 0.57393008 | E10: =+E4/E$5 -> 0.54428213 | F10: =+F4/F$5 -> 0.75359998 | G10: =+G4/G$5 -> 0.641688 | H10: =+H4/H$5 -> 0.51665092 | I10: =+I4/I$5 -> 0.57254305 | ... N10: =+N4/N$5 -> 0.61272096
A13: Row Labels | B13: Sum of 20254 | C13: Sum of 20255 | D13: Sum of 20256 | E13: Sum of 20257 | F13: Sum of 20258 | G13: Sum of 20259 | H13: Sum of 202510 | I13: Sum of 202511 | J13: Sum of 202512 | K13: Sum of 2026 | L13: Sum of 20262 | M13: Sum of 20263
A14: COGS | B14: 539.19 | C14: 486.38 | D14: 805.44 | E14: 2615.38 | F14: 2744.64 | G14: 2810.74 | H14: 4828.72 | I14: 6554.09 | J14: 6772.57 | K14: 32072.6 | L14: 16499.66 | M14: 14980 | N14: =SUM(B14:M14) -> 91709.41
A15: General | B15: 69899.22 | C15: 91831.74 | D15: 111934.19 | E15: 76457.8 | F15: 60816.31 | G15: 113547.76 | H15: 81857.59 | I15: 91656.97 | J15: 102076.79 | K15: 103154.28 | L15: 97629.09 | M15: 111107.66 | N15: =SUM(B15:M15) -> 1111969.4
A16: Personnel | B16: 153155.69 | C16: 157004.96 | D16: 343513.63 | E16: 165312.2 | F16: 188085.27 | G16: 208806.25 | H16: 170715.56 | I16: 195009.97 | J16: 220731.13 | K16: 192121.84 | L16: 180104.82 | M16: 201300.42 | N16: =SUM(B16:M16) -> 2375861.7
A17: Grand Total | B17: 223594.1 | C17: 249323.08 | D17: 456253.26 | E17: 244385.38 | F17: 251646.22 | G17: 325164.75 | H17: 257401.87 | I17: 293221.03 | J17: 329580.49 | K17: 327348.72 | L17: 294233.57 | M17: 327388.08 | N17: =SUM(N14:N16) -> 3579540.5
A19: FY 25/26
A20: COGS | B20: =+B14/B$17 -> 0.0024114679 | C20: =+C14/C$17 -> 0.0019508021 | D20: =+D14/D$17 -> 0.0017653353 | E20: =+E14/E$17 -> 0.010701868 | F20: =+F14/F$17 -> 0.01090674 | G20: =+G14/G$17 -> 0.0086440489 | H20: =+H14/H$17 -> 0.01875946 | I20: =+I14/I$17 -> 0.022352046 | ... N20: =+N14/N$17 -> 0.025620442
A21: General | B21: =+B15/B$17 -> 0.31261657 | C21: =+C15/C$17 -> 0.36832426 | D21: =+D15/D$17 -> 0.24533346 | E21: =+E15/E$17 -> 0.3128575 | F21: =+F15/F$17 -> 0.24167385 | G21: =+G15/G$17 -> 0.34920071 | H21: =+H15/H$17 -> 0.31801474 | I21: =+I15/I$17 -> 0.31258662 | ... N21: =+N15/N$17 -> 0.31064585
A22: Personnel | B22: =+B16/B$17 -> 0.68497196 | C22: =+C16/C$17 -> 0.62972493 | D22: =+D16/D$17 -> 0.75290121 | E22: =+E16/E$17 -> 0.67644063 | F22: =+F16/F$17 -> 0.74741941 | G22: =+G16/G$17 -> 0.64215525 | H22: =+H16/H$17 -> 0.6632258 | I22: =+I16/I$17 -> 0.66506134 | ... N22: =+N16/N$17 -> 0.66373371
A24: FY 26/27
A25: COGS | B25: =+AVERAGE(B20,B8) -> 0.01851117 | C25: =+AVERAGE(C20,C8) -> 0.018279433 | D25: =+AVERAGE(D20,D8) -> 0.075318696 | E25: =+AVERAGE(E20,E8) -> 0.052534645 | F25: =+AVERAGE(F20,F8) -> 0.01464378 | G25: =+AVERAGE(G20,G8) -> 0.017240285 | H25: =+AVERAGE(H20,H8) -> 0.099186387 | I25: =+AVERAGE(I20,I8) -> 0.014726717 | ... N25: =+AVERAGE(N20,N8) -> 0.037685649
A26: General | B26: =+AVERAGE(B21,B9) -> 0.30766762 | C26: =+AVERAGE(C21,C9) -> 0.34287867 | D26: =+AVERAGE(D21,D9) -> 0.26126566 | E26: =+AVERAGE(E21,E9) -> 0.33710398 | F26: =+AVERAGE(F21,F9) -> 0.23484653 | G26: =+AVERAGE(G21,G9) -> 0.34083809 | H26: =+AVERAGE(H21,H9) -> 0.31087525 | I26: =+AVERAGE(I21,I9) -> 0.36647109 | ... N26: =+AVERAGE(N21,N9) -> 0.32408701
A27: Personnel | B27: =+AVERAGE(B22,B10) -> 0.67382121 | C27: =+AVERAGE(C22,C10) -> 0.6388419 | D27: =+AVERAGE(D22,D10) -> 0.66341564 | E27: =+AVERAGE(E22,E10) -> 0.61036138 | F27: =+AVERAGE(F22,F10) -> 0.75050969 | G27: =+AVERAGE(G22,G10) -> 0.64192162 | H27: =+AVERAGE(H22,H10) -> 0.58993836 | I27: =+AVERAGE(I22,I10) -> 0.61880219 | ... N27: =+AVERAGE(N22,N10) -> 0.63822734
A30: Budgeted Costs FY 26/27 | B30: =+'Budget - Overview'!D18 -> 278007 | C30: =+'Budget - Overview'!E18 -> 283315.15 | D30: =+'Budget - Overview'!F18 -> 444389.57 | E30: =+'Budget - Overview'!G18 -> 336795.18 | F30: =+'Budget - Overview'!H18 -> 371554.1 | G30: =+'Budget - Overview'!I18 -> 360228.81 | H30: =+'Budget - Overview'!J18 -> 367677.4 | I30: =+'Budget - Overview'!K18 -> 358217.84 | ... M30: =+'Budget - Overview'!O18 -> 374996.01 | N30: =SUM(B30:M30) -> 4282809.1
A32: FY 26/27
A33: COGS | B33: =+B$30*B25 -> 5146.2348 | C33: =+C$30*C25 -> 5178.8404 | D33: =+D$30*D25 -> 33470.843 | E33: =+E$30*E25 -> 17693.415 | F33: =+F$30*F25 -> 5440.9565 | G33: =+G$30*G25 -> 6210.4473 | H33: =+H$30*H25 -> 36468.592 | I33: =+I$30*I25 -> 5275.3727 | ... M33: =+M$30*M25 -> 9894.8426 | N33: =SUM(B33:M33) -> 161578.81
A34: General | B34: =+B$30*B26 -> 85533.752 | C34: =+C$30*C26 -> 97142.723 | D34: =+D$30*D26 -> 116103.73 | E34: =+E$30*E26 -> 113534.99 | F34: =+F$30*F26 -> 87258.189 | G34: =+G$30*G26 -> 122779.7 | H34: =+H$30*H26 -> 114301.8 | I34: =+I$30*I26 -> 131276.48 | ... M34: =+M$30*M26 -> 130330.86 | N34: =SUM(B34:M34) -> 1389455.7
A35: Personnel | B35: =+B$30*B27 -> 187327.01 | C35: =+C$30*C27 -> 180993.59 | D35: =+D$30*D27 -> 294814.99 | E35: =+E$30*E27 -> 205566.77 | F35: =+F$30*F27 -> 278854.95 | G35: =+G$30*G27 -> 231238.66 | H35: =+H$30*H27 -> 216907 | I35: =+I$30*I27 -> 221665.99 | ... M35: =+M$30*M27 -> 234770.3 | N35: =SUM(B35:M35) -> 2731774.5
